{"3200": {"info": [{"pre_away": "417", "trip_id": "35127933", "pre_dt": "1512350599", "sch_dep_dt": "1512350580", "sch_arr_dt": "1512350580", "trip_name": "8:00 pm from Forest Hills Station to Back Bay Station", "trip_headsign": "Back Bay", "vehicle": {"vehicle_lon": "-71.0988082885742", "vehicle_speed": "0", "vehicle_lat": "42.3363380432129", "vehicle_bearing": "148", "vehicle_timestamp": "1512350133", "vehicle_label": "1253", "vehicle_id": "y1253"}}, {"pre_away": "1065", "trip_id": "35127948", "pre_dt": "1512351247", "sch_dep_dt": "1512351480", "sch_arr_dt": "1512351480", "trip_name": "8:15 pm from Forest Hills Station to Back Bay Station", "trip_headsign": "Back Bay", "vehicle": {"vehicle_lon": "-71.1145172119141", "vehicle_speed": "0", "vehicle_lat": "42.301139831543", "vehicle_bearing": "216", "vehicle_timestamp": "1512350093", "vehicle_label": "1200", "vehicle_id": "y1200"}}, {"pre_away": "1965", "trip_id": "35127949", "pre_dt": "1512352147", "sch_dep_dt": "1512352260", "sch_arr_dt": "1512352260", "trip_name": "8:30 pm from Forest Hills Station to Back Bay Station", "trip_headsign": "Back Bay"}, {"pre_away": "2865", "trip_id": "35127950", "pre_dt": "1512353047", "sch_dep_dt": "1512353160", "sch_arr_dt": "1512353160", "trip_name": "8:45 pm from Forest Hills Station to Back Bay Station", "trip_headsign": "Back Bay"}, {"pre_away": "3836", "trip_id": "35146251", "pre_dt": "1512354018", "sch_dep_dt": "1512354060", "sch_arr_dt": "1512354060", "trip_name": "9:00 pm from Forest Hills Station to Back Bay Station", "trip_headsign": "Back Bay"}], "time": 1512350188.559361}, "3201": {"info": [{"pre_away": "387", "trip_id": "35127933", "pre_dt": "1512350599", "sch_dep_dt": "1512350580", "sch_arr_dt": "1512350580", "trip_name": "8:00 pm from Forest Hills Station to Back Bay Station", "trip_headsign": "Back Bay", "vehicle": {"vehicle_lon": "-71.0988082885742", "vehicle_speed": "0", "vehicle_lat": "42.3363380432129", "vehicle_bearing": "148", "vehicle_timestamp": "1512350133", "vehicle_label": "1253", "vehicle_id": "y1253"}}, {"pre_away": "994", "trip_id": "35127948", "pre_dt": "1512351206", "sch_dep_dt": "1512351480", "sch_arr_dt": "1512351480", "trip_name": "8:15 pm from Forest Hills Station to Back Bay Station", "trip_headsign": "Back Bay", "vehicle": {"vehicle_lon": "-71.1146469116211", "vehicle_speed": "0", "vehicle_lat": "42.3044166564941", "vehicle_bearing": "1", "vehicle_timestamp": "1512350153", "vehicle_label": "1200", "vehicle_id": "y1200"}}, {"pre_away": "1935", "trip_id": "35127949", "pre_dt": "1512352147", "sch_dep_dt": "1512352260", "sch_arr_dt": "1512352260", "trip_name": "8:30 pm from Forest Hills Station to Back Bay Station", "trip_headsign": "Back Bay"}, {"pre_away": "2835", "trip_id": "35127950", "pre_dt": "1512353047", "sch_dep_dt": "1512353160", "sch_arr_dt": "1512353160", "trip_name": "8:45 pm from Forest Hills Station to Back Bay Station", "trip_headsign": "Back Bay"}, {"pre_away": "3806", "trip_id": "35146251", "pre_dt": "1512354018", "sch_dep_dt": "1512354060", "sch_arr_dt": "1512354060", "trip_name": "9:00 pm from Forest Hills Station to Back Bay Station", "trip_headsign": "Back Bay"}], "time": 1512350218.651184}, "3202": {"info": [{"pre_away": "315", "trip_id": "35127933", "pre_dt": "1512350557", "sch_dep_dt": "1512350580", "sch_arr_dt": "1512350580", "trip_name": "8:00 pm from Forest Hills Station to Back Bay Station", "trip_headsign": "Back Bay", "vehicle": {"vehicle_lon": "-71.0910797119141", "vehicle_speed": "0", "vehicle_lat": "42.3395004272461", "vehicle_bearing": "63", "vehicle_timestamp": "1512350194", "vehicle_label": "1253", "vehicle_id": "y1253"}}, {"pre_away": "964", "trip_id": "35127948", "pre_dt": "1512351206", "sch_dep_dt": "1512351480", "sch_arr_dt": "1512351480", "trip_name": "8:15 pm from Forest Hills Station to Back Bay Station", "trip_headsign": "Back Bay", "vehicle": {"vehicle_lon": "-71.1150665283203", "vehicle_speed": "0", "vehicle_lat": "42.3064270019531", "vehicle_bearing": "342", "vehicle_timestamp": "1512350213", "vehicle_label": "1200", "vehicle_id": "y1200"}}, {"pre_away": "1905", "trip_id": "35127949", "pre_dt": "1512352147", "sch_dep_dt": "1512352260", "sch_arr_dt": "1512352260", "trip_name": "8:30 pm from Forest Hills Station to Back Bay Station", "trip_headsign": "Back Bay"}, {"pre_away": "2805", "trip_id": "35127950", "pre_dt": "1512353047", "sch_dep_dt": "1512353160", "sch_arr_dt": "1512353160", "trip_name": "8:45 pm from Forest Hills Station to Back Bay Station", "trip_headsign": "Back Bay"}, {"pre_away": "3776", "trip_id": "35146251", "pre_dt": "1512354018", "sch_dep_dt": "1512354060", "sch_arr_dt": "1512354060", "trip_name": "9:00 pm from Forest Hills Station to Back Bay Station", "trip_headsign": "Back Bay"}], "time": 1512350248.747113}, "3203": {"info": [{"pre_away": "294", "trip_id": "35127933", "pre_dt": "1512350566", "sch_dep_dt": "1512350580", "sch_arr_dt": "1512350580", "trip_name": "8:00 pm from Forest Hills Station to Back Bay Station", "trip_headsign": "Back Bay", "vehicle": {"vehicle_lon": "-71.0881805419922", "vehicle_speed": "0", "vehicle_lat": "42.3406639099121", "vehicle_bearing": "63", "vehicle_timestamp": "1512350232", "vehicle_label": "1253", "vehicle_id": "y1253"}}, {"pre_away": "966", "trip_id": "35127948", "pre_dt": "1512351238", "sch_dep_dt": "1512351480", "sch_arr_dt": "1512351480", "trip_name": "8:15 pm from Forest Hills Station to Back Bay Station", "trip_headsign": "Back Bay", "vehicle": {"vehicle_lon": "-71.1150665283203", "vehicle_speed": "0", "vehicle_lat": "42.3064270019531", "vehicle_bearing": "342", "vehicle_timestamp": "1512350213", "vehicle_label": "1200", "vehicle_id": "y1200"}}, {"pre_away": "1875", "trip_id": "35127949", "pre_dt": "1512352147", "sch_dep_dt": "1512352260", "sch_arr_dt": "1512352260", "trip_name": "8:30 pm from Forest Hills Station to Back Bay Station", "trip_headsign": "Back Bay"}, {"pre_away": "2775", "trip_id": "35127950", "pre_dt": "1512353047", "sch_dep_dt": "1512353160", "sch_arr_dt": "1512353160", "trip_name": "8:45 pm from Forest Hills Station to Back Bay Station", "trip_headsign": "Back Bay"}, {"pre_away": "3746", "trip_id": "35146251", "pre_dt": "1512354018", "sch_dep_dt": "1512354060", "sch_arr_dt": "1512354060", "trip_name": "9:00 pm from Forest Hills Station to Back Bay Station", "trip_headsign": "Back Bay"}], "time": 1512350278.846413}, "3204": {"info": [{"pre_away": "264", "trip_id": "35127933", "pre_dt": "1512350566", "sch_dep_dt": "1512350580", "sch_arr_dt": "1512350580", "trip_name": "8:00 pm from Forest Hills Station to Back Bay Station", "trip_headsign": "Back Bay", "vehicle": {"vehicle_lon": "-71.0881805419922", "vehicle_speed": "0", "vehicle_lat": "42.3406639099121", "vehicle_bearing": "63", "vehicle_timestamp": "1512350232", "vehicle_label": "1253", "vehicle_id": "y1253"}}, {"pre_away": "936", "trip_id": "35127948", "pre_dt": "1512351238", "sch_dep_dt": "1512351480", "sch_arr_dt": "1512351480", "trip_name": "8:15 pm from Forest Hills Station to Back Bay Station", "trip_headsign": "Back Bay", "vehicle": {"vehicle_lon": "-71.1155319213867", "vehicle_speed": "0", "vehicle_lat": "42.3094329833984", "vehicle_bearing": "90", "vehicle_timestamp": "1512350277", "vehicle_label": "1200", "vehicle_id": "y1200"}}, {"pre_away": "1845", "trip_id": "35127949", "pre_dt": "1512352147", "sch_dep_dt": "1512352260", "sch_arr_dt": "1512352260", "trip_name": "8:30 pm from Forest Hills Station to Back Bay Station", "trip_headsign": "Back Bay"}, {"pre_away": "2745", "trip_id": "35127950", "pre_dt": "1512353047", "sch_dep_dt": "1512353160", "sch_arr_dt": "1512353160", "trip_name": "8:45 pm from Forest Hills Station to Back Bay Station", "trip_headsign": "Back Bay"}, {"pre_away": "3716", "trip_id": "35146251", "pre_dt": "1512354018", "sch_dep_dt": "1512354060", "sch_arr_dt": "1512354060", "trip_name": "9:00 pm from Forest Hills Station to Back Bay Station", "trip_headsign": "Back Bay"}], "time": 1512350309.482397}, "3205": {"info": [{"pre_away": "234", "trip_id": "35127933", "pre_dt": "1512350566", "sch_dep_dt": "1512350580", "sch_arr_dt": "1512350580", "trip_name": "8:00 pm from Forest Hills Station to Back Bay Station", "trip_headsign": "Back Bay", "vehicle": {"vehicle_lon": "-71.0881805419922", "vehicle_speed": "0", "vehicle_lat": "42.3406639099121", "vehicle_bearing": "63", "vehicle_timestamp": "1512350232", "vehicle_label": "1253", "vehicle_id": "y1253"}}, {"pre_away": "934", "trip_id": "35127948", "pre_dt": "1512351266", "sch_dep_dt": "1512351480", "sch_arr_dt": "1512351480", "trip_name": "8:15 pm from Forest Hills Station to Back Bay Station", "trip_headsign": "Back Bay", "vehicle": {"vehicle_lon": "-71.1155319213867", "vehicle_speed": "0", "vehicle_lat": "42.3094329833984", "vehicle_bearing": "90", "vehicle_timestamp": "1512350277", "vehicle_label": "1200", "vehicle_id": "y1200"}}, {"pre_away": "1815", "trip_id": "35127949", "pre_dt": "1512352147", "sch_dep_dt": "1512352260", "sch_arr_dt": "1512352260", "trip_name": "8:30 pm from Forest Hills Station to Back Bay Station", "trip_headsign": "Back Bay"}, {"pre_away": "2715", "trip_id": "35127950", "pre_dt": "1512353047", "sch_dep_dt": "1512353160", "sch_arr_dt": "1512353160", "trip_name": "8:45 pm from Forest Hills Station to Back Bay Station", "trip_headsign": "Back Bay"}, {"pre_away": "3686", "trip_id": "35146251", "pre_dt": "1512354018", "sch_dep_dt": "1512354060", "sch_arr_dt": "1512354060", "trip_name": "9:00 pm from Forest Hills Station to Back Bay Station", "trip_headsign": "Back Bay"}], "time": 1512350339.844246}, "3206": {"info": [{"pre_away": "196", "trip_id": "35127933", "pre_dt": "1512350558", "sch_dep_dt": "1512350580", "sch_arr_dt": "1512350580", "trip_name": "8:00 pm from Forest Hills Station to Back Bay Station", "trip_headsign": "Back Bay", "vehicle": {"vehicle_lon": "-71.0828170776367", "vehicle_speed": "0", "vehicle_lat": "42.3444366455078", "vehicle_bearing": "41", "vehicle_timestamp": "1512350295", "vehicle_label": "1253", "vehicle_id": "y1253"}}, {"pre_away": "913", "trip_id": "35127948", "pre_dt": "1512351275", "sch_dep_dt": "1512351480", "sch_arr_dt": "1512351480", "trip_name": "8:15 pm from Forest Hills Station to Back Bay Station", "trip_headsign": "Back Bay", "vehicle": {"vehicle_lon": "-71.1141052246094", "vehicle_speed": "0", "vehicle_lat": "42.312557220459", "vehicle_bearing": "4", "vehicle_timestamp": "1512350338", "vehicle_label": "1200", "vehicle_id": "y1200"}}, {"pre_away": "1785", "trip_id": "35127949", "pre_dt": "1512352147", "sch_dep_dt": "1512352260", "sch_arr_dt": "1512352260", "trip_name": "8:30 pm from Forest Hills Station to Back Bay Station", "trip_headsign": "Back Bay"}, {"pre_away": "2685", "trip_id": "35127950", "pre_dt": "1512353047", "sch_dep_dt": "1512353160", "sch_arr_dt": "1512353160", "trip_name": "8:45 pm from Forest Hills Station to Back Bay Station", "trip_headsign": "Back Bay"}, {"pre_away": "3656", "trip_id": "35146251", "pre_dt": "1512354018", "sch_dep_dt": "1512354060", "sch_arr_dt": "1512354060", "trip_name": "9:00 pm from Forest Hills Station to Back Bay Station", "trip_headsign": "Back Bay"}], "time": 1512350370.161758}, "3207": {"info": [{"pre_away": "166", "trip_id": "35127933", "pre_dt": "1512350558", "sch_dep_dt": "1512350580", "sch_arr_dt": "1512350580", "trip_name": "8:00 pm from Forest Hills Station to Back Bay Station", "trip_headsign": "Back Bay", "vehicle": {"vehicle_lon": "-71.0828170776367", "vehicle_speed": "0", "vehicle_lat": "42.3444366455078", "vehicle_bearing": "41", "vehicle_timestamp": "1512350295", "vehicle_label": "1253", "vehicle_id": "y1253"}}, {"pre_away": "883", "trip_id": "35127948", "pre_dt": "1512351275", "sch_dep_dt": "1512351480", "sch_arr_dt": "1512351480", "trip_name": "8:15 pm from Forest Hills Station to Back Bay Station", "trip_headsign": "Back Bay", "vehicle": {"vehicle_lon": "-71.1141052246094", "vehicle_speed": "0", "vehicle_lat": "42.312557220459", "vehicle_bearing": "4", "vehicle_timestamp": "1512350338", "vehicle_label": "1200", "vehicle_id": "y1200"}}, {"pre_away": "1755", "trip_id": "35127949", "pre_dt": "1512352147", "sch_dep_dt": "1512352260", "sch_arr_dt": "1512352260", "trip_name": "8:30 pm from Forest Hills Station to Back Bay Station", "trip_headsign": "Back Bay"}, {"pre_away": "2655", "trip_id": "35127950", "pre_dt": "1512353047", "sch_dep_dt": "1512353160", "sch_arr_dt": "1512353160", "trip_name": "8:45 pm from Forest Hills Station to Back Bay Station", "trip_headsign": "Back Bay"}, {"pre_away": "3626", "trip_id": "35146251", "pre_dt": "1512354018", "sch_dep_dt": "1512354060", "sch_arr_dt": "1512354060", "trip_name": "9:00 pm from Forest Hills Station to Back Bay Station", "trip_headsign": "Back Bay"}], "time": 1512350400.379181}, "3208": {"info": [{"pre_away": "126", "trip_id": "35127933", "pre_dt": "1512350548", "sch_dep_dt": "1512350580", "sch_arr_dt": "1512350580", "trip_name": "8:00 pm from Forest Hills Station to Back Bay Station", "trip_headsign": "Back Bay", "vehicle": {"vehicle_lon": "-71.0833969116211", "vehicle_speed": "0", "vehicle_lat": "42.3460693359375", "vehicle_bearing": "279", "vehicle_timestamp": "1512350355", "vehicle_label": "1253", "vehicle_id": "y1253"}}, {"pre_away": "860", "trip_id": "35127948", "pre_dt": "1512351282", "sch_dep_dt": "1512351480", "sch_arr_dt": "1512351480", "trip_name": "8:15 pm from Forest Hills Station to Back Bay Station", "trip_headsign": "Back Bay", "vehicle": {"vehicle_lon": "-71.1134414672852", "vehicle_speed": "0", "vehicle_lat": "42.3169097900391", "vehicle_bearing": "27", "vehicle_timestamp": "1512350398", "vehicle_label": "1200", "vehicle_id": "y1200"}}, {"pre_away": "1725", "trip_id": "35127949", "pre_dt": "1512352147", "sch_dep_dt": "1512352260", "sch_arr_dt": "1512352260", "trip_name": "8:30 pm from Forest Hills Station to Back Bay Station", "trip_headsign": "Back Bay"}, {"pre_away": "2625", "trip_id": "35127950", "pre_dt": "1512353047", "sch_dep_dt": "1512353160", "sch_arr_dt": "1512353160", "trip_name": "8:45 pm from Forest Hills Station to Back Bay Station", "trip_headsign": "Back Bay"}, {"pre_away": "3596", "trip_id": "35146251", "pre_dt": "1512354018", "sch_dep_dt": "1512354060", "sch_arr_dt": "1512354060", "trip_name": "9:00 pm from Forest Hills Station to Back Bay Station", "trip_headsign": "Back Bay"}], "time": 1512350430.687409}, "3209": {"info": [{"pre_away": "96", "trip_id": "35127933", "pre_dt": "1512350548", "sch_dep_dt": "1512350580", "sch_arr_dt": "1512350580", "trip_name": "8:00 pm from Forest Hills Station to Back Bay Station", "trip_headsign": "Back Bay", "vehicle": {"vehicle_lon": "-71.0833969116211", "vehicle_speed": "0", "vehicle_lat": "42.3460693359375", "vehicle_bearing": "279", "vehicle_timestamp": "1512350355", "vehicle_label": "1253", "vehicle_id": "y1253"}}, {"pre_away": "830", "trip_id": "35127948", "pre_dt": "1512351282", "sch_dep_dt": "1512351480", "sch_arr_dt": "1512351480", "trip_name": "8:15 pm from Forest Hills Station to Back Bay Station", "trip_headsign": "Back Bay", "vehicle": {"vehicle_lon": "-71.1134414672852", "vehicle_speed": "0", "vehicle_lat": "42.3169097900391", "vehicle_bearing": "27", "vehicle_timestamp": "1512350398", "vehicle_label": "1200", "vehicle_id": "y1200"}}, {"pre_away": "1695", "trip_id": "35127949", "pre_dt": "1512352147", "sch_dep_dt": "1512352260", "sch_arr_dt": "1512352260", "trip_name": "8:30 pm from Forest Hills Station to Back Bay Station", "trip_headsign": "Back Bay"}, {"pre_away": "2595", "trip_id": "35127950", "pre_dt": "1512353047", "sch_dep_dt": "1512353160", "sch_arr_dt": "1512353160", "trip_name": "8:45 pm from Forest Hills Station to Back Bay Station", "trip_headsign": "Back Bay"}, {"pre_away": "3566", "trip_id": "35146251", "pre_dt": "1512354018", "sch_dep_dt": "1512354060", "sch_arr_dt": "1512354060", "trip_name": "9:00 pm from Forest Hills Station to Back Bay Station", "trip_headsign": "Back Bay"}], "time": 1512350460.78386}, "3210": {"info": [{"pre_away": "67", "trip_id": "35127933", "pre_dt": "1512350549", "sch_dep_dt": "1512350580", "sch_arr_dt": "1512350580", "trip_name": "8:00 pm from Forest Hills Station to Back Bay Station", "trip_headsign": "Back Bay", "vehicle": {"vehicle_lon": "-71.0854034423828", "vehicle_speed": "0", "vehicle_lat": "42.3477745056152", "vehicle_bearing": "315", "vehicle_timestamp": "1512350415", "vehicle_label": "1253", "vehicle_id": "y1253"}}, {"pre_away": "784", "trip_id": "35127948", "pre_dt": "1512351266", "sch_dep_dt": "1512351480", "sch_arr_dt": "1512351480", "trip_name": "8:15 pm from Forest Hills Station to Back Bay Station", "trip_headsign": "Back Bay", "vehicle": {"vehicle_lon": "-71.1116409301758", "vehicle_speed": "0", "vehicle_lat": "42.3198623657227", "vehicle_bearing": "352", "vehicle_timestamp": "1512350434", "vehicle_label": "1200", "vehicle_id": "y1200"}}, {"pre_away": "1665", "trip_id": "35127949", "pre_dt": "1512352147", "sch_dep_dt": "1512352260", "sch_arr_dt": "1512352260", "trip_name": "8:30 pm from Forest Hills Station to Back Bay Station", "trip_headsign": "Back Bay"}, {"pre_away": "2565", "trip_id": "35127950", "pre_dt": "1512353047", "sch_dep_dt": "1512353160", "sch_arr_dt": "1512353160", "trip_name": "8:45 pm from Forest Hills Station to Back Bay Station", "trip_headsign": "Back Bay"}, {"pre_away": "3536", "trip_id": "35146251", "pre_dt": "1512354018", "sch_dep_dt": "1512354060", "sch_arr_dt": "1512354060", "trip_name": "9:00 pm from Forest Hills Station to Back Bay Station", "trip_headsign": "Back Bay"}], "time": 1512350490.878493}, "3211": {"info": [{"pre_away": "78", "trip_id": "35127933", "pre_dt": "1512350590", "sch_dep_dt": "1512350580", "sch_arr_dt": "1512350580", "trip_name": "8:00 pm from Forest Hills Station to Back Bay Station", "trip_headsign": "Back Bay", "vehicle": {"vehicle_lon": "-71.0851135253906", "vehicle_speed": "0", "vehicle_lat": "42.348087310791", "vehicle_bearing": "70", "vehicle_timestamp": "1512350469", "vehicle_label": "1253", "vehicle_id": "y1253"}}, {"pre_away": "754", "trip_id": "35127948", "pre_dt": "1512351266", "sch_dep_dt": "1512351480", "sch_arr_dt": "1512351480", "trip_name": "8:15 pm from Forest Hills Station to Back Bay Station", "trip_headsign": "Back Bay", "vehicle": {"vehicle_lon": "-71.1116409301758", "vehicle_speed": "0", "vehicle_lat": "42.3198623657227", "vehicle_bearing": "352", "vehicle_timestamp": "1512350434", "vehicle_label": "1200", "vehicle_id": "y1200"}}, {"pre_away": "1635", "trip_id": "35127949", "pre_dt": "1512352147", "sch_dep_dt": "1512352260", "sch_arr_dt": "1512352260", "trip_name": "8:30 pm from Forest Hills Station to Back Bay Station", "trip_headsign": "Back Bay"}, {"pre_away": "2535", "trip_id": "35127950", "pre_dt": "1512353047", "sch_dep_dt": "1512353160", "sch_arr_dt": "1512353160", "trip_name": "8:45 pm from Forest Hills Station to Back Bay Station", "trip_headsign": "Back Bay"}, {"pre_away": "3506", "trip_id": "35146251", "pre_dt": "1512354018", "sch_dep_dt": "1512354060", "sch_arr_dt": "1512354060", "trip_name": "9:00 pm from Forest Hills Station to Back Bay Station", "trip_headsign": "Back Bay"}], "time": 1512350521.555323}, "3212": {"info": [{"pre_away": "47", "trip_id": "35127933", "pre_dt": "1512350590", "sch_dep_dt": "1512350580", "sch_arr_dt": "1512350580", "trip_name": "8:00 pm from Forest Hills Station to Back Bay Station", "trip_headsign": "Back Bay", "vehicle": {"vehicle_lon": "-71.0851135253906", "vehicle_speed": "0", "vehicle_lat": "42.348087310791", "vehicle_bearing": "70", "vehicle_timestamp": "1512350469", "vehicle_label": "1253", "vehicle_id": "y1253"}}, {"pre_away": "728", "trip_id": "35127948", "pre_dt": "1512351271", "sch_dep_dt": "1512351480", "sch_arr_dt": "1512351480", "trip_name": "8:15 pm from Forest Hills Station to Back Bay Station", "trip_headsign": "Back Bay", "vehicle": {"vehicle_lon": "-71.1121597290039", "vehicle_speed": "0", "vehicle_lat": "42.3236274719238", "vehicle_bearing": "358", "vehicle_timestamp": "1512350495", "vehicle_label": "1200", "vehicle_id": "y1200"}}, {"pre_away": "1604", "trip_id": "35127949", "pre_dt": "1512352147", "sch_dep_dt": "1512352260", "sch_arr_dt": "1512352260", "trip_name": "8:30 pm from Forest Hills Station to Back Bay Station", "trip_headsign": "Back Bay"}, {"pre_away": "2504", "trip_id": "35127950", "pre_dt": "1512353047", "sch_dep_dt": "1512353160", "sch_arr_dt": "1512353160", "trip_name": "8:45 pm from Forest Hills Station to Back Bay Station", "trip_headsign": "Back Bay"}, {"pre_away": "3475", "trip_id": "35146251", "pre_dt": "1512354018", "sch_dep_dt": "1512354060", "sch_arr_dt": "1512354060", "trip_name": "9:00 pm from Forest Hills Station to Back Bay Station", "trip_headsign": "Back Bay"}], "time": 1512350551.651996}, "3213": {"info": [{"pre_away": "17", "trip_id": "35127933", "pre_dt": "1512350590", "sch_dep_dt": "1512350580", "sch_arr_dt": "1512350580", "trip_name": "8:00 pm from Forest Hills Station to Back Bay Station", "trip_headsign": "Back Bay", "vehicle": {"vehicle_lon": "-71.0851135253906", "vehicle_speed": "0", "vehicle_lat": "42.348087310791", "vehicle_bearing": "70", "vehicle_timestamp": "1512350469", "vehicle_label": "1253", "vehicle_id": "y1253"}}, {"pre_away": "698", "trip_id": "35127948", "pre_dt": "1512351271", "sch_dep_dt": "1512351480", "sch_arr_dt": "1512351480", "trip_name": "8:15 pm from Forest Hills Station to Back Bay Station", "trip_headsign": "Back Bay", "vehicle": {"vehicle_lon": "-71.1121597290039", "vehicle_speed": "0", "vehicle_lat": "42.3236274719238", "vehicle_bearing": "358", "vehicle_timestamp": "1512350495", "vehicle_label": "1200", "vehicle_id": "y1200"}}, {"pre_away": "1574", "trip_id": "35127949", "pre_dt": "1512352147", "sch_dep_dt": "1512352260", "sch_arr_dt": "1512352260", "trip_name": "8:30 pm from Forest Hills Station to Back Bay Station", "trip_headsign": "Back Bay"}, {"pre_away": "2474", "trip_id": "35127950", "pre_dt": "1512353047", "sch_dep_dt": "1512353160", "sch_arr_dt": "1512353160", "trip_name": "8:45 pm from Forest Hills Station to Back Bay Station", "trip_headsign": "Back Bay"}, {"pre_away": "3445", "trip_id": "35146251", "pre_dt": "1512354018", "sch_dep_dt": "1512354060", "sch_arr_dt": "1512354060", "trip_name": "9:00 pm from Forest Hills Station to Back Bay Station", "trip_headsign": "Back Bay"}], "time": 1512350581.750812}, "3214": {"info": [{"pre_away": "671", "trip_id": "35127948", "pre_dt": "1512351274", "sch_dep_dt": "1512351480", "sch_arr_dt": "1512351480", "trip_name": "8:15 pm from Forest Hills Station to Back Bay Station", "trip_headsign": "Back Bay", "vehicle": {"vehicle_lon": "-71.1107330322266", "vehicle_speed": "0", "vehicle_lat": "42.3290748596191", "vehicle_bearing": "345", "vehicle_timestamp": "1512350561", "vehicle_label": "1200", "vehicle_id": "y1200"}}, {"pre_away": "1544", "trip_id": "35127949", "pre_dt": "1512352147", "sch_dep_dt": "1512352260", "sch_arr_dt": "1512352260", "trip_name": "8:30 pm from Forest Hills Station to Back Bay Station", "trip_headsign": "Back Bay"}, {"pre_away": "2444", "trip_id": "35127950", "pre_dt": "1512353047", "sch_dep_dt": "1512353160", "sch_arr_dt": "1512353160", "trip_name": "8:45 pm from Forest Hills Station to Back Bay Station", "trip_headsign": "Back Bay"}, {"pre_away": "3415", "trip_id": "35146251", "pre_dt": "1512354018", "sch_dep_dt": "1512354060", "sch_arr_dt": "1512354060", "trip_name": "9:00 pm from Forest Hills Station to Back Bay Station", "trip_headsign": "Back Bay"}], "time": 1512350612.187689}, "3215": {"info": [{"pre_away": "641", "trip_id": "35127948", "pre_dt": "1512351274", "sch_dep_dt": "1512351480", "sch_arr_dt": "1512351480", "trip_name": "8:15 pm from Forest Hills Station to Back Bay Station", "trip_headsign": "Back Bay", "vehicle": {"vehicle_lon": "-71.1107330322266", "vehicle_speed": "0", "vehicle_lat": "42.3290748596191", "vehicle_bearing": "345", "vehicle_timestamp": "1512350561", "vehicle_label": "1200", "vehicle_id": "y1200"}}, {"pre_away": "1514", "trip_id": "35127949", "pre_dt": "1512352147", "sch_dep_dt": "1512352260", "sch_arr_dt": "1512352260", "trip_name": "8:30 pm from Forest Hills Station to Back Bay Station", "trip_headsign": "Back Bay"}, {"pre_away": "2414", "trip_id": "35127950", "pre_dt": "1512353047", "sch_dep_dt": "1512353160", "sch_arr_dt": "1512353160", "trip_name": "8:45 pm from Forest Hills Station to Back Bay Station", "trip_headsign": "Back Bay"}, {"pre_away": "3385", "trip_id": "35146251", "pre_dt": "1512354018", "sch_dep_dt": "1512354060", "sch_arr_dt": "1512354060", "trip_name": "9:00 pm from Forest Hills Station to Back Bay Station", "trip_headsign": "Back Bay"}], "time": 1512350642.284663}, "3216": {"info": [{"pre_away": "619", "trip_id": "35127948", "pre_dt": "1512351282", "sch_dep_dt": "1512351480", "sch_arr_dt": "1512351480", "trip_name": "8:15 pm from Forest Hills Station to Back Bay Station", "trip_headsign": "Back Bay", "vehicle": {"vehicle_lon": "-71.1119003295898", "vehicle_speed": "0", "vehicle_lat": "42.3318099975586", "vehicle_bearing": "345", "vehicle_timestamp": "1512350622", "vehicle_label": "1200", "vehicle_id": "y1200"}}, {"pre_away": "1484", "trip_id": "35127949", "pre_dt": "1512352147", "sch_dep_dt": "1512352260", "sch_arr_dt": "1512352260", "trip_name": "8:30 pm from Forest Hills Station to Back Bay Station", "trip_headsign": "Back Bay"}, {"pre_away": "2384", "trip_id": "35127950", "pre_dt": "1512353047", "sch_dep_dt": "1512353160", "sch_arr_dt": "1512353160", "trip_name": "8:45 pm from Forest Hills Station to Back Bay Station", "trip_headsign": "Back Bay"}, {"pre_away": "3355", "trip_id": "35146251", "pre_dt": "1512354018", "sch_dep_dt": "1512354060", "sch_arr_dt": "1512354060", "trip_name": "9:00 pm from Forest Hills Station to Back Bay Station", "trip_headsign": "Back Bay"}], "time": 1512350672.375812}, "3217": {"info": [{"pre_away": "589", "trip_id": "35127948", "pre_dt": "1512351282", "sch_dep_dt": "1512351480", "sch_arr_dt": "1512351480", "trip_name": "8:15 pm from Forest Hills Station to Back Bay Station", "trip_headsign": "Back Bay", "vehicle": {"vehicle_lon": "-71.1119003295898", "vehicle_speed": "0", "vehicle_lat": "42.3318099975586", "vehicle_bearing": "345", "vehicle_timestamp": "1512350622", "vehicle_label": "1200", "vehicle_id": "y1200"}}, {"pre_away": "1454", "trip_id": "35127949", "pre_dt": "1512352147", "sch_dep_dt": "1512352260", "sch_arr_dt": "1512352260", "trip_name": "8:30 pm from Forest Hills Station to Back Bay Station", "trip_headsign": "Back Bay"}, {"pre_away": "2354", "trip_id": "35127950", "pre_dt": "1512353047", "sch_dep_dt": "1512353160", "sch_arr_dt": "1512353160", "trip_name": "8:45 pm from Forest Hills Station to Back Bay Station", "trip_headsign": "Back Bay"}, {"pre_away": "3325", "trip_id": "35146251", "pre_dt": "1512354018", "sch_dep_dt": "1512354060", "sch_arr_dt": "1512354060", "trip_name": "9:00 pm from Forest Hills Station to Back Bay Station", "trip_headsign": "Back Bay"}], "time": 1512350702.787103}, "3218": {"info": [{"pre_away": "590", "trip_id": "35127948", "pre_dt": "1512351313", "sch_dep_dt": "1512351480", "sch_arr_dt": "1512351480", "trip_name": "8:15 pm from Forest Hills Station to Back Bay Station", "trip_headsign": "Back Bay", "vehicle": {"vehicle_lon": "-71.1108245849609", "vehicle_speed": "0", "vehicle_lat": "42.3327293395996", "vehicle_bearing": "51", "vehicle_timestamp": "1512350682", "vehicle_label": "1200", "vehicle_id": "y1200"}}, {"pre_away": "1424", "trip_id": "35127949", "pre_dt": "1512352147", "sch_dep_dt": "1512352260", "sch_arr_dt": "1512352260", "trip_name": "8:30 pm from Forest Hills Station to Back Bay Station", "trip_headsign": "Back Bay"}, {"pre_away": "2324", "trip_id": "35127950", "pre_dt": "1512353047", "sch_dep_dt": "1512353160", "sch_arr_dt": "1512353160", "trip_name": "8:45 pm from Forest Hills Station to Back Bay Station", "trip_headsign": "Back Bay"}, {"pre_away": "3295", "trip_id": "35146251", "pre_dt": "1512354018", "sch_dep_dt": "1512354060", "sch_arr_dt": "1512354060", "trip_name": "9:00 pm from Forest Hills Station to Back Bay Station", "trip_headsign": "Back Bay"}], "time": 1512350733.063099}, "3219": {"info": [{"pre_away": "560", "trip_id": "35127948", "pre_dt": "1512351313", "sch_dep_dt": "1512351480", "sch_arr_dt": "1512351480", "trip_name": "8:15 pm from Forest Hills Station to Back Bay Station", "trip_headsign": "Back Bay", "vehicle": {"vehicle_lon": "-71.1108245849609", "vehicle_speed": "0", "vehicle_lat": "42.3327293395996", "vehicle_bearing": "51", "vehicle_timestamp": "1512350682", "vehicle_label": "1200", "vehicle_id": "y1200"}}, {"pre_away": "1394", "trip_id": "35127949", "pre_dt": "1512352147", "sch_dep_dt": "1512352260", "sch_arr_dt": "1512352260", "trip_name": "8:30 pm from Forest Hills Station to Back Bay Station", "trip_headsign": "Back Bay"}, {"pre_away": "2294", "trip_id": "35127950", "pre_dt": "1512353047", "sch_dep_dt": "1512353160", "sch_arr_dt": "1512353160", "trip_name": "8:45 pm from Forest Hills Station to Back Bay Station", "trip_headsign": "Back Bay"}, {"pre_away": "3265", "trip_id": "35146251", "pre_dt": "1512354018", "sch_dep_dt": "1512354060", "sch_arr_dt": "1512354060", "trip_name": "9:00 pm from Forest Hills Station to Back Bay Station", "trip_headsign": "Back Bay"}], "time": 1512350763.244961}, "3220": {"info": [{"pre_away": "550", "trip_id": "35127948", "pre_dt": "1512351333", "sch_dep_dt": "1512351480", "sch_arr_dt": "1512351480", "trip_name": "8:15 pm from Forest Hills Station to Back Bay Station", "trip_headsign": "Back Bay", "vehicle": {"vehicle_lon": "-71.1079635620117", "vehicle_speed": "0", "vehicle_lat": "42.3332290649414", "vehicle_bearing": "91", "vehicle_timestamp": "1512350742", "vehicle_label": "1200", "vehicle_id": "y1200"}}, {"pre_away": "1364", "trip_id": "35127949", "pre_dt": "1512352147", "sch_dep_dt": "1512352260", "sch_arr_dt": "1512352260", "trip_name": "8:30 pm from Forest Hills Station to Back Bay Station", "trip_headsign": "Back Bay"}, {"pre_away": "2264", "trip_id": "35127950", "pre_dt": "1512353047", "sch_dep_dt": "1512353160", "sch_arr_dt": "1512353160", "trip_name": "8:45 pm from Forest Hills Station to Back Bay Station", "trip_headsign": "Back Bay"}, {"pre_away": "3235", "trip_id": "35146251", "pre_dt": "1512354018", "sch_dep_dt": "1512354060", "sch_arr_dt": "1512354060", "trip_name": "9:00 pm from Forest Hills Station to Back Bay Station", "trip_headsign": "Back Bay"}], "time": 1512350793.570947}, "3221": {"info": [{"pre_away": "527", "trip_id": "35127948", "pre_dt": "1512351340", "sch_dep_dt": "1512351480", "sch_arr_dt": "1512351480", "trip_name": "8:15 pm from Forest Hills Station to Back Bay Station", "trip_headsign": "Back Bay", "vehicle": {"vehicle_lon": "-71.1052627563477", "vehicle_speed": "0", "vehicle_lat": "42.3338890075684", "vehicle_bearing": "64", "vehicle_timestamp": "1512350787", "vehicle_label": "1200", "vehicle_id": "y1200"}}, {"pre_away": "1337", "trip_id": "35127949", "pre_dt": "1512352150", "sch_dep_dt": "1512352260", "sch_arr_dt": "1512352260", "trip_name": "8:30 pm from Forest Hills Station to Back Bay Station", "trip_headsign": "Back Bay"}, {"pre_away": "2234", "trip_id": "35127950", "pre_dt": "1512353047", "sch_dep_dt": "1512353160", "sch_arr_dt": "1512353160", "trip_name": "8:45 pm from Forest Hills Station to Back Bay Station", "trip_headsign": "Back Bay"}, {"pre_away": "3205", "trip_id": "35146251", "pre_dt": "1512354018", "sch_dep_dt": "1512354060", "sch_arr_dt": "1512354060", "trip_name": "9:00 pm from Forest Hills Station to Back Bay Station", "trip_headsign": "Back Bay"}], "time": 1512350823.67305}, "3222": {"info": [{"pre_away": "496", "trip_id": "35127948", "pre_dt": "1512351340", "sch_dep_dt": "1512351480", "sch_arr_dt": "1512351480", "trip_name": "8:15 pm from Forest Hills Station to Back Bay Station", "trip_headsign": "Back Bay", "vehicle": {"vehicle_lon": "-71.1052627563477", "vehicle_speed": "0", "vehicle_lat": "42.3338890075684", "vehicle_bearing": "64", "vehicle_timestamp": "1512350787", "vehicle_label": "1200", "vehicle_id": "y1200"}}, {"pre_away": "1306", "trip_id": "35127949", "pre_dt": "1512352150", "sch_dep_dt": "1512352260", "sch_arr_dt": "1512352260", "trip_name": "8:30 pm from Forest Hills Station to Back Bay Station", "trip_headsign": "Back Bay"}, {"pre_away": "2203", "trip_id": "35127950", "pre_dt": "1512353047", "sch_dep_dt": "1512353160", "sch_arr_dt": "1512353160", "trip_name": "8:45 pm from Forest Hills Station to Back Bay Station", "trip_headsign": "Back Bay"}, {"pre_away": "3174", "trip_id": "35146251", "pre_dt": "1512354018", "sch_dep_dt": "1512354060", "sch_arr_dt": "1512354060", "trip_name": "9:00 pm from Forest Hills Station to Back Bay Station", "trip_headsign": "Back Bay"}], "time": 1512350853.767992}, "3223": {"info": [{"pre_away": "478", "trip_id": "35127948", "pre_dt": "1512351352", "sch_dep_dt": "1512351480", "sch_arr_dt": "1512351480", "trip_name": "8:15 pm from Forest Hills Station to Back Bay Station", "trip_headsign": "Back Bay", "vehicle": {"vehicle_lon": "-71.1022109985352", "vehicle_speed": "0", "vehicle_lat": "42.3350524902344", "vehicle_bearing": "66", "vehicle_timestamp": "1512350847", "vehicle_label": "1200", "vehicle_id": "y1200"}}, {"pre_away": "1293", "trip_id": "35127949", "pre_dt": "1512352167", "sch_dep_dt": "1512352260", "sch_arr_dt": "1512352260", "trip_name": "8:30 pm from Forest Hills Station to Back Bay Station", "trip_headsign": "Back Bay"}, {"pre_away": "2173", "trip_id": "35127950", "pre_dt": "1512353047", "sch_dep_dt": "1512353160", "sch_arr_dt": "1512353160", "trip_name": "8:45 pm from Forest Hills Station to Back Bay Station", "trip_headsign": "Back Bay"}, {"pre_away": "3144", "trip_id": "35146251", "pre_dt": "1512354018", "sch_dep_dt": "1512354060", "sch_arr_dt": "1512354060", "trip_name": "9:00 pm from Forest Hills Station to Back Bay Station", "trip_headsign": "Back Bay"}], "time": 1512350883.868875}, "3224": {"info": [{"pre_away": "448", "trip_id": "35127948", "pre_dt": "1512351352", "sch_dep_dt": "1512351480", "sch_arr_dt": "1512351480", "trip_name": "8:15 pm from Forest Hills Station to Back Bay Station", "trip_headsign": "Back Bay", "vehicle": {"vehicle_lon": "-71.1022109985352", "vehicle_speed": "0", "vehicle_lat": "42.3350524902344", "vehicle_bearing": "66", "vehicle_timestamp": "1512350847", "vehicle_label": "1200", "vehicle_id": "y1200"}}, {"pre_away": "1263", "trip_id": "35127949", "pre_dt": "1512352167", "sch_dep_dt": "1512352260", "sch_arr_dt": "1512352260", "trip_name": "8:30 pm from Forest Hills Station to Back Bay Station", "trip_headsign": "Back Bay"}, {"pre_away": "2143", "trip_id": "35127950", "pre_dt": "1512353047", "sch_dep_dt": "1512353160", "sch_arr_dt": "1512353160", "trip_name": "8:45 pm from Forest Hills Station to Back Bay Station", "trip_headsign": "Back Bay"}, {"pre_away": "3114", "trip_id": "35146251", "pre_dt": "1512354018", "sch_dep_dt": "1512354060", "sch_arr_dt": "1512354060", "trip_name": "9:00 pm from Forest Hills Station to Back Bay Station", "trip_headsign": "Back Bay"}], "time": 1512350913.962692}, "3225": {"info": [{"pre_away": "418", "trip_id": "35127948", "pre_dt": "1512351352", "sch_dep_dt": "1512351480", "sch_arr_dt": "1512351480", "trip_name": "8:15 pm from Forest Hills Station to Back Bay Station", "trip_headsign": "Back Bay", "vehicle": {"vehicle_lon": "-71.1022109985352", "vehicle_speed": "0", "vehicle_lat": "42.3350524902344", "vehicle_bearing": "66", "vehicle_timestamp": "1512350847", "vehicle_label": "1200", "vehicle_id": "y1200"}}, {"pre_away": "1261", "trip_id": "35127949", "pre_dt": "1512352195", "sch_dep_dt": "1512352260", "sch_arr_dt": "1512352260", "trip_name": "8:30 pm from Forest Hills Station to Back Bay Station", "trip_headsign": "Back Bay"}, {"pre_away": "2113", "trip_id": "35127950", "pre_dt": "1512353047", "sch_dep_dt": "1512353160", "sch_arr_dt": "1512353160", "trip_name": "8:45 pm from Forest Hills Station to Back Bay Station", "trip_headsign": "Back Bay"}, {"pre_away": "3084", "trip_id": "35146251", "pre_dt": "1512354018", "sch_dep_dt": "1512354060", "sch_arr_dt": "1512354060", "trip_name": "9:00 pm from Forest Hills Station to Back Bay Station", "trip_headsign": "Back Bay"}], "time": 1512350944.064544}, "3226": {"info": [{"pre_away": "418", "trip_id": "35127948", "pre_dt": "1512351382", "sch_dep_dt": "1512351480", "sch_arr_dt": "1512351480", "trip_name": "8:15 pm from Forest Hills Station to Back Bay Station", "trip_headsign": "Back Bay", "vehicle": {"vehicle_lon": "-71.1003036499023", "vehicle_speed": "0", "vehicle_lat": "42.3357162475586", "vehicle_bearing": "60", "vehicle_timestamp": "1512350907", "vehicle_label": "1200", "vehicle_id": "y1200"}}, {"pre_away": "1228", "trip_id": "35127949", "pre_dt": "1512352192", "sch_dep_dt": "1512352260", "sch_arr_dt": "1512352260", "trip_name": "8:30 pm from Forest Hills Station to Back Bay Station", "trip_headsign": "Back Bay"}, {"pre_away": "2083", "trip_id": "35127950", "pre_dt": "1512353047", "sch_dep_dt": "1512353160", "sch_arr_dt": "1512353160", "trip_name": "8:45 pm from Forest Hills Station to Back Bay Station", "trip_headsign": "Back Bay"}, {"pre_away": "3054", "trip_id": "35146251", "pre_dt": "1512354018", "sch_dep_dt": "1512354060", "sch_arr_dt": "1512354060", "trip_name": "9:00 pm from Forest Hills Station to Back Bay Station", "trip_headsign": "Back Bay"}], "time": 1512350974.158709}, "3227": {"info": [{"pre_away": "387", "trip_id": "35127948", "pre_dt": "1512351382", "sch_dep_dt": "1512351480", "sch_arr_dt": "1512351480", "trip_name": "8:15 pm from Forest Hills Station to Back Bay Station", "trip_headsign": "Back Bay", "vehicle": {"vehicle_lon": "-71.1003036499023", "vehicle_speed": "0", "vehicle_lat": "42.3357162475586", "vehicle_bearing": "60", "vehicle_timestamp": "1512350907", "vehicle_label": "1200", "vehicle_id": "y1200"}}, {"pre_away": "1197", "trip_id": "35127949", "pre_dt": "1512352192", "sch_dep_dt": "1512352260", "sch_arr_dt": "1512352260", "trip_name": "8:30 pm from Forest Hills Station to Back Bay Station", "trip_headsign": "Back Bay"}, {"pre_away": "2052", "trip_id": "35127950", "pre_dt": "1512353047", "sch_dep_dt": "1512353160", "sch_arr_dt": "1512353160", "trip_name": "8:45 pm from Forest Hills Station to Back Bay Station", "trip_headsign": "Back Bay"}, {"pre_away": "3023", "trip_id": "35146251", "pre_dt": "1512354018", "sch_dep_dt": "1512354060", "sch_arr_dt": "1512354060", "trip_name": "9:00 pm from Forest Hills Station to Back Bay Station", "trip_headsign": "Back Bay"}], "time": 1512351004.25899}, "3228": {"info": [{"pre_away": "422", "trip_id": "35127948", "pre_dt": "1512351447", "sch_dep_dt": "1512351480", "sch_arr_dt": "1512351480", "trip_name": "8:15 pm from Forest Hills Station to Back Bay Station", "trip_headsign": "Back Bay", "vehicle": {"vehicle_lon": "-71.0988006591797", "vehicle_speed": "0", "vehicle_lat": "42.3363647460938", "vehicle_bearing": "148", "vehicle_timestamp": "1512350981", "vehicle_label": "1200", "vehicle_id": "y1200"}}, {"pre_away": "1167", "trip_id": "35127949", "pre_dt": "1512352192", "sch_dep_dt": "1512352260", "sch_arr_dt": "1512352260", "trip_name": "8:30 pm from Forest Hills Station to Back Bay Station", "trip_headsign": "Back Bay"}, {"pre_away": "2022", "trip_id": "35127950", "pre_dt": "1512353047", "sch_dep_dt": "1512353160", "sch_arr_dt": "1512353160", "trip_name": "8:45 pm from Forest Hills Station to Back Bay Station", "trip_headsign": "Back Bay"}, {"pre_away": "2993", "trip_id": "35146251", "pre_dt": "1512354018", "sch_dep_dt": "1512354060", "sch_arr_dt": "1512354060", "trip_name": "9:00 pm from Forest Hills Station to Back Bay Station", "trip_headsign": "Back Bay"}], "time": 1512351034.451759}, "3229": {"info": [{"pre_away": "392", "trip_id": "35127948", "pre_dt": "1512351447", "sch_dep_dt": "1512351480", "sch_arr_dt": "1512351480", "trip_name": "8:15 pm from Forest Hills Station to Back Bay Station", "trip_headsign": "Back Bay", "vehicle": {"vehicle_lon": "-71.0988006591797", "vehicle_speed": "0", "vehicle_lat": "42.3363647460938", "vehicle_bearing": "148", "vehicle_timestamp": "1512350981", "vehicle_label": "1200", "vehicle_id": "y1200"}}, {"pre_away": "1155", "trip_id": "35127949", "pre_dt": "1512352210", "sch_dep_dt": "1512352260", "sch_arr_dt": "1512352260", "trip_name": "8:30 pm from Forest Hills Station to Back Bay Station", "trip_headsign": "Back Bay"}, {"pre_away": "1992", "trip_id": "35127950", "pre_dt": "1512353047", "sch_dep_dt": "1512353160", "sch_arr_dt": "1512353160", "trip_name": "8:45 pm from Forest Hills Station to Back Bay Station", "trip_headsign": "Back Bay"}, {"pre_away": "2963", "trip_id": "35146251", "pre_dt": "1512354018", "sch_dep_dt": "1512354060", "sch_arr_dt": "1512354060", "trip_name": "9:00 pm from Forest Hills Station to Back Bay Station", "trip_headsign": "Back Bay"}], "time": 1512351064.546038}, "3230": {"info": [{"pre_away": "372", "trip_id": "35127948", "pre_dt": "1512351457", "sch_dep_dt": "1512351480", "sch_arr_dt": "1512351480", "trip_name": "8:15 pm from Forest Hills Station to Back Bay Station", "trip_headsign": "Back Bay", "vehicle": {"vehicle_lon": "-71.0956802368164", "vehicle_speed": "0", "vehicle_lat": "42.3375244140625", "vehicle_bearing": "64", "vehicle_timestamp": "1512351042", "vehicle_label": "1200", "vehicle_id": "y1200"}}, {"pre_away": "1095", "trip_id": "35127949", "pre_dt": "1512352180", "sch_dep_dt": "1512352260", "sch_arr_dt": "1512352260", "trip_name": "8:30 pm from Forest Hills Station to Back Bay Station", "trip_headsign": "Back Bay", "vehicle": {"vehicle_lon": "-71.1149520874023", "vehicle_speed": "0", "vehicle_lat": "42.2998504638672", "vehicle_bearing": "216", "vehicle_timestamp": "1512351033", "vehicle_label": "1203", "vehicle_id": "y1203"}}, {"pre_away": "1962", "trip_id": "35127950", "pre_dt": "1512353047", "sch_dep_dt": "1512353160", "sch_arr_dt": "1512353160", "trip_name": "8:45 pm from Forest Hills Station to Back Bay Station", "trip_headsign": "Back Bay"}, {"pre_away": "2933", "trip_id": "35146251", "pre_dt": "1512354018", "sch_dep_dt": "1512354060", "sch_arr_dt": "1512354060", "trip_name": "9:00 pm from Forest Hills Station to Back Bay Station", "trip_headsign": "Back Bay"}], "time": 1512351094.766012}, "3231": {"info": [{"pre_away": "341", "trip_id": "35127948", "pre_dt": "1512351457", "sch_dep_dt": "1512351480", "sch_arr_dt": "1512351480", "trip_name": "8:15 pm from Forest Hills Station to Back Bay Station", "trip_headsign": "Back Bay", "vehicle": {"vehicle_lon": "-71.0956802368164", "vehicle_speed": "0", "vehicle_lat": "42.3375244140625", "vehicle_bearing": "64", "vehicle_timestamp": "1512351042", "vehicle_label": "1200", "vehicle_id": "y1200"}}, {"pre_away": "1064", "trip_id": "35127949", "pre_dt": "1512352180", "sch_dep_dt": "1512352260", "sch_arr_dt": "1512352260", "trip_name": "8:30 pm from Forest Hills Station to Back Bay Station", "trip_headsign": "Back Bay", "vehicle": {"vehicle_lon": "-71.1149520874023", "vehicle_speed": "0", "vehicle_lat": "42.2998504638672", "vehicle_bearing": "216", "vehicle_timestamp": "1512351033", "vehicle_label": "1203", "vehicle_id": "y1203"}}, {"pre_away": "1931", "trip_id": "35127950", "pre_dt": "1512353047", "sch_dep_dt": "1512353160", "sch_arr_dt": "1512353160", "trip_name": "8:45 pm from Forest Hills Station to Back Bay Station", "trip_headsign": "Back Bay"}, {"pre_away": "2902", "trip_id": "35146251", "pre_dt": "1512354018", "sch_dep_dt": "1512354060", "sch_arr_dt": "1512354060", "trip_name": "9:00 pm from Forest Hills Station to Back Bay Station", "trip_headsign": "Back Bay"}], "time": 1512351126.074901}, "3232": {"info": [{"pre_away": "330", "trip_id": "35127948", "pre_dt": "1512351476", "sch_dep_dt": "1512351480", "sch_arr_dt": "1512351480", "trip_name": "8:15 pm from Forest Hills Station to Back Bay Station", "trip_headsign": "Back Bay", "vehicle": {"vehicle_lon": "-71.0920791625977", "vehicle_speed": "0", "vehicle_lat": "42.3389587402344", "vehicle_bearing": "63", "vehicle_timestamp": "1512351102", "vehicle_label": "1200", "vehicle_id": "y1200"}}, {"pre_away": "1095", "trip_id": "35127949", "pre_dt": "1512352241", "sch_dep_dt": "1512352260", "sch_arr_dt": "1512352260", "trip_name": "8:30 pm from Forest Hills Station to Back Bay Station", "trip_headsign": "Back Bay", "vehicle": {"vehicle_lon": "-71.1144561767578", "vehicle_speed": "0", "vehicle_lat": "42.2998046875", "vehicle_bearing": "216", "vehicle_timestamp": "1512351094", "vehicle_label": "1203", "vehicle_id": "y1203"}}, {"pre_away": "1901", "trip_id": "35127950", "pre_dt": "1512353047", "sch_dep_dt": "1512353160", "sch_arr_dt": "1512353160", "trip_name": "8:45 pm from Forest Hills Station to Back Bay Station", "trip_headsign": "Back Bay"}, {"pre_away": "2872", "trip_id": "35146251", "pre_dt": "1512354018", "sch_dep_dt": "1512354060", "sch_arr_dt": "1512354060", "trip_name": "9:00 pm from Forest Hills Station to Back Bay Station", "trip_headsign": "Back Bay"}], "time": 1512351156.42252}, "3233": {"info": [{"pre_away": "300", "trip_id": "35127948", "pre_dt": "1512351476", "sch_dep_dt": "1512351480", "sch_arr_dt": "1512351480", "trip_name": "8:15 pm from Forest Hills Station to Back Bay Station", "trip_headsign": "Back Bay", "vehicle": {"vehicle_lon": "-71.0891342163086", "vehicle_speed": "0", "vehicle_lat": "42.3401565551758", "vehicle_bearing": "60", "vehicle_timestamp": "1512351162", "vehicle_label": "1200", "vehicle_id": "y1200"}}, {"pre_away": "1065", "trip_id": "35127949", "pre_dt": "1512352241", "sch_dep_dt": "1512352260", "sch_arr_dt": "1512352260", "trip_name": "8:30 pm from Forest Hills Station to Back Bay Station", "trip_headsign": "Back Bay", "vehicle": {"vehicle_lon": "-71.1144561767578", "vehicle_speed": "0", "vehicle_lat": "42.2998046875", "vehicle_bearing": "216", "vehicle_timestamp": "1512351094", "vehicle_label": "1203", "vehicle_id": "y1203"}}, {"pre_away": "1871", "trip_id": "35127950", "pre_dt": "1512353047", "sch_dep_dt": "1512353160", "sch_arr_dt": "1512353160", "trip_name": "8:45 pm from Forest Hills Station to Back Bay Station", "trip_headsign": "Back Bay"}, {"pre_away": "2842", "trip_id": "35146251", "pre_dt": "1512354018", "sch_dep_dt": "1512354060", "sch_arr_dt": "1512354060", "trip_name": "9:00 pm from Forest Hills Station to Back Bay Station", "trip_headsign": "Back Bay"}], "time": 1512351186.748884}, "3234": {"info": [{"pre_away": "310", "trip_id": "35127948", "pre_dt": "1512351516", "sch_dep_dt": "1512351480", "sch_arr_dt": "1512351480", "trip_name": "8:15 pm from Forest Hills Station to Back Bay Station", "trip_headsign": "Back Bay", "vehicle": {"vehicle_lon": "-71.0883712768555", "vehicle_speed": "0", "vehicle_lat": "42.3404731750488", "vehicle_bearing": "63", "vehicle_timestamp": "1512351179", "vehicle_label": "1200", "vehicle_id": "y1200"}}, {"pre_away": "1035", "trip_id": "35127949", "pre_dt": "1512352241", "sch_dep_dt": "1512352260", "sch_arr_dt": "1512352260", "trip_name": "8:30 pm from Forest Hills Station to Back Bay Station", "trip_headsign": "Back Bay", "vehicle": {"vehicle_lon": "-71.1144561767578", "vehicle_speed": "0", "vehicle_lat": "42.2998046875", "vehicle_bearing": "216", "vehicle_timestamp": "1512351094", "vehicle_label": "1203", "vehicle_id": "y1203"}}, {"pre_away": "1841", "trip_id": "35127950", "pre_dt": "1512353047", "sch_dep_dt": "1512353160", "sch_arr_dt": "1512353160", "trip_name": "8:45 pm from Forest Hills Station to Back Bay Station", "trip_headsign": "Back Bay"}, {"pre_away": "2812", "trip_id": "35146251", "pre_dt": "1512354018", "sch_dep_dt": "1512354060", "sch_arr_dt": "1512354060", "trip_name": "9:00 pm from Forest Hills Station to Back Bay Station", "trip_headsign": "Back Bay"}], "time": 1512351216.882389}, "3235": {"info": [{"pre_away": "280", "trip_id": "35127948", "pre_dt": "1512351516", "sch_dep_dt": "1512351480", "sch_arr_dt": "1512351480", "trip_name": "8:15 pm from Forest Hills Station to Back Bay Station", "trip_headsign": "Back Bay", "vehicle": {"vehicle_lon": "-71.0883712768555", "vehicle_speed": "0", "vehicle_lat": "42.3404731750488", "vehicle_bearing": "63", "vehicle_timestamp": "1512351179", "vehicle_label": "1200", "vehicle_id": "y1200"}}, {"pre_away": "1005", "trip_id": "35127949", "pre_dt": "1512352241", "sch_dep_dt": "1512352260", "sch_arr_dt": "1512352260", "trip_name": "8:30 pm from Forest Hills Station to Back Bay Station", "trip_headsign": "Back Bay", "vehicle": {"vehicle_lon": "-71.1144561767578", "vehicle_speed": "0", "vehicle_lat": "42.2998046875", "vehicle_bearing": "216", "vehicle_timestamp": "1512351094", "vehicle_label": "1203", "vehicle_id": "y1203"}}, {"pre_away": "1811", "trip_id": "35127950", "pre_dt": "1512353047", "sch_dep_dt": "1512353160", "sch_arr_dt": "1512353160", "trip_name": "8:45 pm from Forest Hills Station to Back Bay Station", "trip_headsign": "Back Bay"}, {"pre_away": "2782", "trip_id": "35146251", "pre_dt": "1512354018", "sch_dep_dt": "1512354060", "sch_arr_dt": "1512354060", "trip_name": "9:00 pm from Forest Hills Station to Back Bay Station", "trip_headsign": "Back Bay"}], "time": 1512351247.004204}, "3236": {"info": [{"pre_away": "257", "trip_id": "35127948", "pre_dt": "1512351523", "sch_dep_dt": "1512351480", "sch_arr_dt": "1512351480", "trip_name": "8:15 pm from Forest Hills Station to Back Bay Station", "trip_headsign": "Back Bay", "vehicle": {"vehicle_lon": "-71.084228515625", "vehicle_speed": "0", "vehicle_lat": "42.3433380126953", "vehicle_bearing": "42", "vehicle_timestamp": "1512351239", "vehicle_label": "1200", "vehicle_id": "y1200"}}, {"pre_away": "1038", "trip_id": "35127949", "pre_dt": "1512352304", "sch_dep_dt": "1512352260", "sch_arr_dt": "1512352260", "trip_name": "8:30 pm from Forest Hills Station to Back Bay Station", "trip_headsign": "Back Bay", "vehicle": {"vehicle_lon": "-71.1143951416016", "vehicle_speed": "0", "vehicle_lat": "42.3016319274902", "vehicle_bearing": "287", "vehicle_timestamp": "1512351214", "vehicle_label": "1203", "vehicle_id": "y1203"}}, {"pre_away": "1781", "trip_id": "35127950", "pre_dt": "1512353047", "sch_dep_dt": "1512353160", "sch_arr_dt": "1512353160", "trip_name": "8:45 pm from Forest Hills Station to Back Bay Station", "trip_headsign": "Back Bay"}, {"pre_away": "2752", "trip_id": "35146251", "pre_dt": "1512354018", "sch_dep_dt": "1512354060", "sch_arr_dt": "1512354060", "trip_name": "9:00 pm from Forest Hills Station to Back Bay Station", "trip_headsign": "Back Bay"}], "time": 1512351277.143873}, "3237": {"info": [{"pre_away": "226", "trip_id": "35127948", "pre_dt": "1512351523", "sch_dep_dt": "1512351480", "sch_arr_dt": "1512351480", "trip_name": "8:15 pm from Forest Hills Station to Back Bay Station", "trip_headsign": "Back Bay", "vehicle": {"vehicle_lon": "-71.084228515625", "vehicle_speed": "0", "vehicle_lat": "42.3433380126953", "vehicle_bearing": "42", "vehicle_timestamp": "1512351239", "vehicle_label": "1200", "vehicle_id": "y1200"}}, {"pre_away": "1007", "trip_id": "35127949", "pre_dt": "1512352304", "sch_dep_dt": "1512352260", "sch_arr_dt": "1512352260", "trip_name": "8:30 pm from Forest Hills Station to Back Bay Station", "trip_headsign": "Back Bay", "vehicle": {"vehicle_lon": "-71.1143951416016", "vehicle_speed": "0", "vehicle_lat": "42.3016319274902", "vehicle_bearing": "287", "vehicle_timestamp": "1512351214", "vehicle_label": "1203", "vehicle_id": "y1203"}}, {"pre_away": "1750", "trip_id": "35127950", "pre_dt": "1512353047", "sch_dep_dt": "1512353160", "sch_arr_dt": "1512353160", "trip_name": "8:45 pm from Forest Hills Station to Back Bay Station", "trip_headsign": "Back Bay"}, {"pre_away": "2721", "trip_id": "35146251", "pre_dt": "1512354018", "sch_dep_dt": "1512354060", "sch_arr_dt": "1512354060", "trip_name": "9:00 pm from Forest Hills Station to Back Bay Station", "trip_headsign": "Back Bay"}], "time": 1512351309.549984}, "3238": {"info": [{"pre_away": "213", "trip_id": "35127948", "pre_dt": "1512351540", "sch_dep_dt": "1512351480", "sch_arr_dt": "1512351480", "trip_name": "8:15 pm from Forest Hills Station to Back Bay Station", "trip_headsign": "Back Bay", "vehicle": {"vehicle_lon": "-71.0821685791016", "vehicle_speed": "0", "vehicle_lat": "42.3450508117676", "vehicle_bearing": "41", "vehicle_timestamp": "1512351300", "vehicle_label": "1200", "vehicle_id": "y1200"}}, {"pre_away": "979", "trip_id": "35127949", "pre_dt": "1512352306", "sch_dep_dt": "1512352260", "sch_arr_dt": "1512352260", "trip_name": "8:30 pm from Forest Hills Station to Back Bay Station", "trip_headsign": "Back Bay", "vehicle": {"vehicle_lon": "-71.1148529052734", "vehicle_speed": "0", "vehicle_lat": "42.3059768676758", "vehicle_bearing": "339", "vehicle_timestamp": "1512351274", "vehicle_label": "1203", "vehicle_id": "y1203"}}, {"pre_away": "1720", "trip_id": "35127950", "pre_dt": "1512353047", "sch_dep_dt": "1512353160", "sch_arr_dt": "1512353160", "trip_name": "8:45 pm from Forest Hills Station to Back Bay Station", "trip_headsign": "Back Bay"}, {"pre_away": "2691", "trip_id": "35146251", "pre_dt": "1512354018", "sch_dep_dt": "1512354060", "sch_arr_dt": "1512354060", "trip_name": "9:00 pm from Forest Hills Station to Back Bay Station", "trip_headsign": "Back Bay"}], "time": 1512351339.641525}, "3239": {"info": [{"pre_away": "183", "trip_id": "35127948", "pre_dt": "1512351540", "sch_dep_dt": "1512351480", "sch_arr_dt": "1512351480", "trip_name": "8:15 pm from Forest Hills Station to Back Bay Station", "trip_headsign": "Back Bay", "vehicle": {"vehicle_lon": "-71.0821685791016", "vehicle_speed": "0", "vehicle_lat": "42.3450508117676", "vehicle_bearing": "41", "vehicle_timestamp": "1512351300", "vehicle_label": "1200", "vehicle_id": "y1200"}}, {"pre_away": "946", "trip_id": "35127949", "pre_dt": "1512352303", "sch_dep_dt": "1512352260", "sch_arr_dt": "1512352260", "trip_name": "8:30 pm from Forest Hills Station to Back Bay Station", "trip_headsign": "Back Bay", "vehicle": {"vehicle_lon": "-71.1155319213867", "vehicle_speed": "0", "vehicle_lat": "42.3094329833984", "vehicle_bearing": "90", "vehicle_timestamp": "1512351314", "vehicle_label": "1203", "vehicle_id": "y1203"}}, {"pre_away": "1690", "trip_id": "35127950", "pre_dt": "1512353047", "sch_dep_dt": "1512353160", "sch_arr_dt": "1512353160", "trip_name": "8:45 pm from Forest Hills Station to Back Bay Station", "trip_headsign": "Back Bay"}, {"pre_away": "2661", "trip_id": "35146251", "pre_dt": "1512354018", "sch_dep_dt": "1512354060", "sch_arr_dt": "1512354060", "trip_name": "9:00 pm from Forest Hills Station to Back Bay Station", "trip_headsign": "Back Bay"}], "time": 1512351369.83775}, "3240": {"info": [{"pre_away": "178", "trip_id": "35127948", "pre_dt": "1512351565", "sch_dep_dt": "1512351480", "sch_arr_dt": "1512351480", "trip_name": "8:15 pm from Forest Hills Station to Back Bay Station", "trip_headsign": "Back Bay", "vehicle": {"vehicle_lon": "-71.0827255249023", "vehicle_speed": "0", "vehicle_lat": "42.3458251953125", "vehicle_bearing": "281", "vehicle_timestamp": "1512351360", "vehicle_label": "1200", "vehicle_id": "y1200"}}, {"pre_away": "920", "trip_id": "35127949", "pre_dt": "1512352307", "sch_dep_dt": "1512352260", "sch_arr_dt": "1512352260", "trip_name": "8:30 pm from Forest Hills Station to Back Bay Station", "trip_headsign": "Back Bay", "vehicle": {"vehicle_lon": "-71.1155319213867", "vehicle_speed": "0", "vehicle_lat": "42.3094329833984", "vehicle_bearing": "90", "vehicle_timestamp": "1512351314", "vehicle_label": "1203", "vehicle_id": "y1203"}}, {"pre_away": "1660", "trip_id": "35127950", "pre_dt": "1512353047", "sch_dep_dt": "1512353160", "sch_arr_dt": "1512353160", "trip_name": "8:45 pm from Forest Hills Station to Back Bay Station", "trip_headsign": "Back Bay"}, {"pre_away": "2631", "trip_id": "35146251", "pre_dt": "1512354018", "sch_dep_dt": "1512354060", "sch_arr_dt": "1512354060", "trip_name": "9:00 pm from Forest Hills Station to Back Bay Station", "trip_headsign": "Back Bay"}], "time": 1512351400.156006}, "3241": {"info": [{"pre_away": "148", "trip_id": "35127948", "pre_dt": "1512351565", "sch_dep_dt": "1512351480", "sch_arr_dt": "1512351480", "trip_name": "8:15 pm from Forest Hills Station to Back Bay Station", "trip_headsign": "Back Bay", "vehicle": {"vehicle_lon": "-71.0827255249023", "vehicle_speed": "0", "vehicle_lat": "42.3458251953125", "vehicle_bearing": "281", "vehicle_timestamp": "1512351360", "vehicle_label": "1200", "vehicle_id": "y1200"}}, {"pre_away": "890", "trip_id": "35127949", "pre_dt": "1512352307", "sch_dep_dt": "1512352260", "sch_arr_dt": "1512352260", "trip_name": "8:30 pm from Forest Hills Station to Back Bay Station", "trip_headsign": "Back Bay", "vehicle": {"vehicle_lon": "-71.1140594482422", "vehicle_speed": "0", "vehicle_lat": "42.3129959106445", "vehicle_bearing": "4", "vehicle_timestamp": "1512351375", "vehicle_label": "1203", "vehicle_id": "y1203"}}, {"pre_away": "1630", "trip_id": "35127950", "pre_dt": "1512353047", "sch_dep_dt": "1512353160", "sch_arr_dt": "1512353160", "trip_name": "8:45 pm from Forest Hills Station to Back Bay Station", "trip_headsign": "Back Bay"}, {"pre_away": "2601", "trip_id": "35146251", "pre_dt": "1512354018", "sch_dep_dt": "1512354060", "sch_arr_dt": "1512354060", "trip_name": "9:00 pm from Forest Hills Station to Back Bay Station", "trip_headsign": "Back Bay"}], "time": 1512351430.431822}, "3242": {"info": [{"pre_away": "113", "trip_id": "35127948", "pre_dt": "1512351560", "sch_dep_dt": "1512351480", "sch_arr_dt": "1512351480", "trip_name": "8:15 pm from Forest Hills Station to Back Bay Station", "trip_headsign": "Back Bay", "vehicle": {"vehicle_lon": "-71.0854644775391", "vehicle_speed": "0", "vehicle_lat": "42.3476371765137", "vehicle_bearing": "340", "vehicle_timestamp": "1512351420", "vehicle_label": "1200", "vehicle_id": "y1200"}}, {"pre_away": "860", "trip_id": "35127949", "pre_dt": "1512352307", "sch_dep_dt": "1512352260", "sch_arr_dt": "1512352260", "trip_name": "8:30 pm from Forest Hills Station to Back Bay Station", "trip_headsign": "Back Bay", "vehicle": {"vehicle_lon": "-71.1140594482422", "vehicle_speed": "0", "vehicle_lat": "42.3129959106445", "vehicle_bearing": "4", "vehicle_timestamp": "1512351375", "vehicle_label": "1203", "vehicle_id": "y1203"}}, {"pre_away": "1600", "trip_id": "35127950", "pre_dt": "1512353047", "sch_dep_dt": "1512353160", "sch_arr_dt": "1512353160", "trip_name": "8:45 pm from Forest Hills Station to Back Bay Station", "trip_headsign": "Back Bay"}, {"pre_away": "2571", "trip_id": "35146251", "pre_dt": "1512354018", "sch_dep_dt": "1512354060", "sch_arr_dt": "1512354060", "trip_name": "9:00 pm from Forest Hills Station to Back Bay Station", "trip_headsign": "Back Bay"}, {"pre_away": "3400", "trip_id": "35146250", "pre_dt": "1512354847", "sch_dep_dt": "1512354960", "sch_arr_dt": "1512354960", "trip_name": "9:15 pm from Forest Hills Station to Back Bay Station", "trip_headsign": "Back Bay"}], "time": 1512351460.763714}, "3243": {"info": [{"pre_away": "83", "trip_id": "35127948", "pre_dt": "1512351560", "sch_dep_dt": "1512351480", "sch_arr_dt": "1512351480", "trip_name": "8:15 pm from Forest Hills Station to Back Bay Station", "trip_headsign": "Back Bay", "vehicle": {"vehicle_lon": "-71.0854644775391", "vehicle_speed": "0", "vehicle_lat": "42.3476371765137", "vehicle_bearing": "340", "vehicle_timestamp": "1512351420", "vehicle_label": "1200", "vehicle_id": "y1200"}}, {"pre_away": "844", "trip_id": "35127949", "pre_dt": "1512352321", "sch_dep_dt": "1512352260", "sch_arr_dt": "1512352260", "trip_name": "8:30 pm from Forest Hills Station to Back Bay Station", "trip_headsign": "Back Bay", "vehicle": {"vehicle_lon": "-71.1135482788086", "vehicle_speed": "0", "vehicle_lat": "42.3167877197266", "vehicle_bearing": "27", "vehicle_timestamp": "1512351435", "vehicle_label": "1203", "vehicle_id": "y1203"}}, {"pre_away": "1570", "trip_id": "35127950", "pre_dt": "1512353047", "sch_dep_dt": "1512353160", "sch_arr_dt": "1512353160", "trip_name": "8:45 pm from Forest Hills Station to Back Bay Station", "trip_headsign": "Back Bay"}, {"pre_away": "2541", "trip_id": "35146251", "pre_dt": "1512354018", "sch_dep_dt": "1512354060", "sch_arr_dt": "1512354060", "trip_name": "9:00 pm from Forest Hills Station to Back Bay Station", "trip_headsign": "Back Bay"}, {"pre_away": "3370", "trip_id": "35146250", "pre_dt": "1512354847", "sch_dep_dt": "1512354960", "sch_arr_dt": "1512354960", "trip_name": "9:15 pm from Forest Hills Station to Back Bay Station", "trip_headsign": "Back Bay"}], "time": 1512351490.968853}, "3244": {"info": [{"pre_away": "64", "trip_id": "35127948", "pre_dt": "1512351572", "sch_dep_dt": "1512351480", "sch_arr_dt": "1512351480", "trip_name": "8:15 pm from Forest Hills Station to Back Bay Station", "trip_headsign": "Back Bay", "vehicle": {"vehicle_lon": "-71.0844497680664", "vehicle_speed": "0", "vehicle_lat": "42.3481483459473", "vehicle_bearing": "70", "vehicle_timestamp": "1512351460", "vehicle_label": "1200", "vehicle_id": "y1200"}}, {"pre_away": "790", "trip_id": "35127949", "pre_dt": "1512352298", "sch_dep_dt": "1512352260", "sch_arr_dt": "1512352260", "trip_name": "8:30 pm from Forest Hills Station to Back Bay Station", "trip_headsign": "Back Bay", "vehicle": {"vehicle_lon": "-71.1116409301758", "vehicle_speed": "0", "vehicle_lat": "42.3199234008789", "vehicle_bearing": "350", "vehicle_timestamp": "1512351467", "vehicle_label": "1203", "vehicle_id": "y1203"}}, {"pre_away": "1539", "trip_id": "35127950", "pre_dt": "1512353047", "sch_dep_dt": "1512353160", "sch_arr_dt": "1512353160", "trip_name": "8:45 pm from Forest Hills Station to Back Bay Station", "trip_headsign": "Back Bay"}, {"pre_away": "2510", "trip_id": "35146251", "pre_dt": "1512354018", "sch_dep_dt": "1512354060", "sch_arr_dt": "1512354060", "trip_name": "9:00 pm from Forest Hills Station to Back Bay Station", "trip_headsign": "Back Bay"}, {"pre_away": "3339", "trip_id": "35146250", "pre_dt": "1512354847", "sch_dep_dt": "1512354960", "sch_arr_dt": "1512354960", "trip_name": "9:15 pm from Forest Hills Station to Back Bay Station", "trip_headsign": "Back Bay"}], "time": 1512351521.107235}, "3245": {"info": [{"pre_away": "71", "trip_id": "35127948", "pre_dt": "1512351609", "sch_dep_dt": "1512351480", "sch_arr_dt": "1512351480", "trip_name": "8:15 pm from Forest Hills Station to Back Bay Station", "trip_headsign": "Back Bay", "vehicle": {"vehicle_lon": "-71.0844497680664", "vehicle_speed": "0", "vehicle_lat": "42.3481483459473", "vehicle_bearing": "70", "vehicle_timestamp": "1512351460", "vehicle_label": "1200", "vehicle_id": "y1200"}}, {"pre_away": "760", "trip_id": "35127949", "pre_dt": "1512352298", "sch_dep_dt": "1512352260", "sch_arr_dt": "1512352260", "trip_name": "8:30 pm from Forest Hills Station to Back Bay Station", "trip_headsign": "Back Bay", "vehicle": {"vehicle_lon": "-71.1116409301758", "vehicle_speed": "0", "vehicle_lat": "42.3199234008789", "vehicle_bearing": "350", "vehicle_timestamp": "1512351467", "vehicle_label": "1203", "vehicle_id": "y1203"}}, {"pre_away": "1509", "trip_id": "35127950", "pre_dt": "1512353047", "sch_dep_dt": "1512353160", "sch_arr_dt": "1512353160", "trip_name": "8:45 pm from Forest Hills Station to Back Bay Station", "trip_headsign": "Back Bay"}, {"pre_away": "2480", "trip_id": "35146251", "pre_dt": "1512354018", "sch_dep_dt": "1512354060", "sch_arr_dt": "1512354060", "trip_name": "9:00 pm from Forest Hills Station to Back Bay Station", "trip_headsign": "Back Bay"}, {"pre_away": "3309", "trip_id": "35146250", "pre_dt": "1512354847", "sch_dep_dt": "1512354960", "sch_arr_dt": "1512354960", "trip_name": "9:15 pm from Forest Hills Station to Back Bay Station", "trip_headsign": "Back Bay"}], "time": 1512351551.658501}, "3246": {"info": [{"pre_away": "41", "trip_id": "35127948", "pre_dt": "1512351609", "sch_dep_dt": "1512351480", "sch_arr_dt": "1512351480", "trip_name": "8:15 pm from Forest Hills Station to Back Bay Station", "trip_headsign": "Back Bay", "vehicle": {"vehicle_lon": "-71.0828323364258", "vehicle_speed": "0", "vehicle_lat": "42.3486289978027", "vehicle_bearing": "69", "vehicle_timestamp": "1512351521", "vehicle_label": "1200", "vehicle_id": "y1200"}}, {"pre_away": "713", "trip_id": "35127949", "pre_dt": "1512352281", "sch_dep_dt": "1512352260", "sch_arr_dt": "1512352260", "trip_name": "8:30 pm from Forest Hills Station to Back Bay Station", "trip_headsign": "Back Bay", "vehicle": {"vehicle_lon": "-71.1106643676758", "vehicle_speed": "0", "vehicle_lat": "42.3285865783691", "vehicle_bearing": "0", "vehicle_timestamp": "1512351556", "vehicle_label": "1203", "vehicle_id": "y1203"}}, {"pre_away": "1479", "trip_id": "35127950", "pre_dt": "1512353047", "sch_dep_dt": "1512353160", "sch_arr_dt": "1512353160", "trip_name": "8:45 pm from Forest Hills Station to Back Bay Station", "trip_headsign": "Back Bay"}, {"pre_away": "2450", "trip_id": "35146251", "pre_dt": "1512354018", "sch_dep_dt": "1512354060", "sch_arr_dt": "1512354060", "trip_name": "9:00 pm from Forest Hills Station to Back Bay Station", "trip_headsign": "Back Bay"}, {"pre_away": "3279", "trip_id": "35146250", "pre_dt": "1512354847", "sch_dep_dt": "1512354960", "sch_arr_dt": "1512354960", "trip_name": "9:15 pm from Forest Hills Station to Back Bay Station", "trip_headsign": "Back Bay"}], "time": 1512351581.7607}, "3247": {"info": [{"pre_away": "11", "trip_id": "35127948", "pre_dt": "1512351609", "sch_dep_dt": "1512351480", "sch_arr_dt": "1512351480", "trip_name": "8:15 pm from Forest Hills Station to Back Bay Station", "trip_headsign": "Back Bay", "vehicle": {"vehicle_lon": "-71.0828323364258", "vehicle_speed": "0", "vehicle_lat": "42.3486289978027", "vehicle_bearing": "69", "vehicle_timestamp": "1512351521", "vehicle_label": "1200", "vehicle_id": "y1200"}}, {"pre_away": "678", "trip_id": "35127949", "pre_dt": "1512352276", "sch_dep_dt": "1512352260", "sch_arr_dt": "1512352260", "trip_name": "8:30 pm from Forest Hills Station to Back Bay Station", "trip_headsign": "Back Bay", "vehicle": {"vehicle_lon": "-71.1107406616211", "vehicle_speed": "0", "vehicle_lat": "42.3290328979492", "vehicle_bearing": "345", "vehicle_timestamp": "1512351563", "vehicle_label": "1203", "vehicle_id": "y1203"}}, {"pre_away": "1449", "trip_id": "35127950", "pre_dt": "1512353047", "sch_dep_dt": "1512353160", "sch_arr_dt": "1512353160", "trip_name": "8:45 pm from Forest Hills Station to Back Bay Station", "trip_headsign": "Back Bay"}, {"pre_away": "2420", "trip_id": "35146251", "pre_dt": "1512354018", "sch_dep_dt": "1512354060", "sch_arr_dt": "1512354060", "trip_name": "9:00 pm from Forest Hills Station to Back Bay Station", "trip_headsign": "Back Bay"}, {"pre_away": "3249", "trip_id": "35146250", "pre_dt": "1512354847", "sch_dep_dt": "1512354960", "sch_arr_dt": "1512354960", "trip_name": "9:15 pm from Forest Hills Station to Back Bay Station", "trip_headsign": "Back Bay"}], "time": 1512351612.90811}, "3248": {"info": [{"pre_away": "21", "trip_id": "35127948", "pre_dt": "1512351649", "sch_dep_dt": "1512351480", "sch_arr_dt": "1512351480", "trip_name": "8:15 pm from Forest Hills Station to Back Bay Station", "trip_headsign": "Back Bay", "vehicle": {"vehicle_lon": "-71.0813751220703", "vehicle_speed": "0", "vehicle_lat": "42.3490257263184", "vehicle_bearing": "71", "vehicle_timestamp": "1512351581", "vehicle_label": "1200", "vehicle_id": "y1200"}}, {"pre_away": "648", "trip_id": "35127949", "pre_dt": "1512352276", "sch_dep_dt": "1512352260", "sch_arr_dt": "1512352260", "trip_name": "8:30 pm from Forest Hills Station to Back Bay Station", "trip_headsign": "Back Bay", "vehicle": {"vehicle_lon": "-71.1107406616211", "vehicle_speed": "0", "vehicle_lat": "42.3290328979492", "vehicle_bearing": "345", "vehicle_timestamp": "1512351563", "vehicle_label": "1203", "vehicle_id": "y1203"}}, {"pre_away": "1419", "trip_id": "35127950", "pre_dt": "1512353047", "sch_dep_dt": "1512353160", "sch_arr_dt": "1512353160", "trip_name": "8:45 pm from Forest Hills Station to Back Bay Station", "trip_headsign": "Back Bay", "vehicle": {"vehicle_lon": "-71.1148529052734", "vehicle_speed": "0", "vehicle_lat": "42.2998695373535", "vehicle_bearing": "216", "vehicle_timestamp": "1512351575", "vehicle_label": "1264", "vehicle_id": "y1264"}}, {"pre_away": "2390", "trip_id": "35146251", "pre_dt": "1512354018", "sch_dep_dt": "1512354060", "sch_arr_dt": "1512354060", "trip_name": "9:00 pm from Forest Hills Station to Back Bay Station", "trip_headsign": "Back Bay"}, {"pre_away": "3219", "trip_id": "35146250", "pre_dt": "1512354847", "sch_dep_dt": "1512354960", "sch_arr_dt": "1512354960", "trip_name": "9:15 pm from Forest Hills Station to Back Bay Station", "trip_headsign": "Back Bay"}], "time": 1512351643.084884}, "3249": {"info": [{"pre_away": "600", "trip_id": "35127949", "pre_dt": "1512352259", "sch_dep_dt": "1512352260", "sch_arr_dt": "1512352260", "trip_name": "8:30 pm from Forest Hills Station to Back Bay Station", "trip_headsign": "Back Bay", "vehicle": {"vehicle_lon": "-71.1109771728516", "vehicle_speed": "0", "vehicle_lat": "42.3326301574707", "vehicle_bearing": "51", "vehicle_timestamp": "1512351624", "vehicle_label": "1203", "vehicle_id": "y1203"}}, {"pre_away": "1388", "trip_id": "35127950", "pre_dt": "1512353047", "sch_dep_dt": "1512353160", "sch_arr_dt": "1512353160", "trip_name": "8:45 pm from Forest Hills Station to Back Bay Station", "trip_headsign": "Back Bay", "vehicle": {"vehicle_lon": "-71.1148529052734", "vehicle_speed": "0", "vehicle_lat": "42.2998695373535", "vehicle_bearing": "216", "vehicle_timestamp": "1512351575", "vehicle_label": "1264", "vehicle_id": "y1264"}}, {"pre_away": "2359", "trip_id": "35146251", "pre_dt": "1512354018", "sch_dep_dt": "1512354060", "sch_arr_dt": "1512354060", "trip_name": "9:00 pm from Forest Hills Station to Back Bay Station", "trip_headsign": "Back Bay"}, {"pre_away": "3188", "trip_id": "35146250", "pre_dt": "1512354847", "sch_dep_dt": "1512354960", "sch_arr_dt": "1512354960", "trip_name": "9:15 pm from Forest Hills Station to Back Bay Station", "trip_headsign": "Back Bay"}], "time": 1512351673.231139}}