{"3840": {"info": [{"pre_away": "1135", "trip_id": "35272360", "pre_dt": "1512532532", "sch_dep_dt": "1512532680", "sch_arr_dt": "1512532680", "trip_name": "10:36 pm from Forest Hills Station to Back Bay Station", "trip_headsign": "Back Bay", "vehicle": {"vehicle_lon": "-71.1143493652344", "vehicle_speed": "0", "vehicle_lat": "42.2998123168945", "vehicle_bearing": "216", "vehicle_timestamp": "1512531322", "vehicle_label": "1640", "vehicle_id": "y1640"}}, {"pre_away": "1868", "trip_id": "35272399", "pre_dt": "1512533265", "sch_dep_dt": "1512533280", "sch_arr_dt": "1512533280", "trip_name": "10:48 pm from Forest Hills Station to Back Bay Station", "trip_headsign": "Back Bay"}, {"pre_away": "3295", "trip_id": "35272378", "pre_dt": "1512534692", "sch_dep_dt": "1512534540", "sch_arr_dt": "1512534540", "trip_name": "11:12 pm from Forest Hills Station to Back Bay Station", "trip_headsign": "Back Bay"}, {"pre_away": "4735", "trip_id": "35272363", "pre_dt": "1512536132", "sch_dep_dt": "1512535980", "sch_arr_dt": "1512535980", "trip_name": "11:36 pm from Forest Hills Station to Back Bay Station", "trip_headsign": "Back Bay"}], "time": 1512531404.301268}, "3841": {"info": [{"pre_away": "1104", "trip_id": "35272360", "pre_dt": "1512532532", "sch_dep_dt": "1512532680", "sch_arr_dt": "1512532680", "trip_name": "10:36 pm from Forest Hills Station to Back Bay Station", "trip_headsign": "Back Bay", "vehicle": {"vehicle_lon": "-71.1143493652344", "vehicle_speed": "0", "vehicle_lat": "42.2998123168945", "vehicle_bearing": "216", "vehicle_timestamp": "1512531322", "vehicle_label": "1640", "vehicle_id": "y1640"}}, {"pre_away": "1837", "trip_id": "35272399", "pre_dt": "1512533265", "sch_dep_dt": "1512533280", "sch_arr_dt": "1512533280", "trip_name": "10:48 pm from Forest Hills Station to Back Bay Station", "trip_headsign": "Back Bay"}, {"pre_away": "3264", "trip_id": "35272378", "pre_dt": "1512534692", "sch_dep_dt": "1512534540", "sch_arr_dt": "1512534540", "trip_name": "11:12 pm from Forest Hills Station to Back Bay Station", "trip_headsign": "Back Bay"}, {"pre_away": "4704", "trip_id": "35272363", "pre_dt": "1512536132", "sch_dep_dt": "1512535980", "sch_arr_dt": "1512535980", "trip_name": "11:36 pm from Forest Hills Station to Back Bay Station", "trip_headsign": "Back Bay"}], "time": 1512531434.453444}, "3842": {"info": [{"pre_away": "1074", "trip_id": "35272360", "pre_dt": "1512532532", "sch_dep_dt": "1512532680", "sch_arr_dt": "1512532680", "trip_name": "10:36 pm from Forest Hills Station to Back Bay Station", "trip_headsign": "Back Bay", "vehicle": {"vehicle_lon": "-71.1143493652344", "vehicle_speed": "0", "vehicle_lat": "42.2998123168945", "vehicle_bearing": "216", "vehicle_timestamp": "1512531322", "vehicle_label": "1640", "vehicle_id": "y1640"}}, {"pre_away": "1831", "trip_id": "35272399", "pre_dt": "1512533289", "sch_dep_dt": "1512533280", "sch_arr_dt": "1512533280", "trip_name": "10:48 pm from Forest Hills Station to Back Bay Station", "trip_headsign": "Back Bay"}, {"pre_away": "3234", "trip_id": "35272378", "pre_dt": "1512534692", "sch_dep_dt": "1512534540", "sch_arr_dt": "1512534540", "trip_name": "11:12 pm from Forest Hills Station to Back Bay Station", "trip_headsign": "Back Bay"}, {"pre_away": "4674", "trip_id": "35272363", "pre_dt": "1512536132", "sch_dep_dt": "1512535980", "sch_arr_dt": "1512535980", "trip_name": "11:36 pm from Forest Hills Station to Back Bay Station", "trip_headsign": "Back Bay"}], "time": 1512531464.602443}, "3843": {"info": [{"pre_away": "1011", "trip_id": "35272360", "pre_dt": "1512532499", "sch_dep_dt": "1512532680", "sch_arr_dt": "1512532680", "trip_name": "10:36 pm from Forest Hills Station to Back Bay Station", "trip_headsign": "Back Bay", "vehicle": {"vehicle_lon": "-71.1146621704102", "vehicle_speed": "0", "vehicle_lat": "42.3046875", "vehicle_bearing": "4", "vehicle_timestamp": "1512531442", "vehicle_label": "1640", "vehicle_id": "y1640"}}, {"pre_away": "1802", "trip_id": "35272399", "pre_dt": "1512533290", "sch_dep_dt": "1512533280", "sch_arr_dt": "1512533280", "trip_name": "10:48 pm from Forest Hills Station to Back Bay Station", "trip_headsign": "Back Bay"}, {"pre_away": "3204", "trip_id": "35272378", "pre_dt": "1512534692", "sch_dep_dt": "1512534540", "sch_arr_dt": "1512534540", "trip_name": "11:12 pm from Forest Hills Station to Back Bay Station", "trip_headsign": "Back Bay"}, {"pre_away": "4644", "trip_id": "35272363", "pre_dt": "1512536132", "sch_dep_dt": "1512535980", "sch_arr_dt": "1512535980", "trip_name": "11:36 pm from Forest Hills Station to Back Bay Station", "trip_headsign": "Back Bay"}], "time": 1512531494.754315}, "3844": {"info": [{"pre_away": "981", "trip_id": "35272360", "pre_dt": "1512532499", "sch_dep_dt": "1512532680", "sch_arr_dt": "1512532680", "trip_name": "10:36 pm from Forest Hills Station to Back Bay Station", "trip_headsign": "Back Bay", "vehicle": {"vehicle_lon": "-71.1146621704102", "vehicle_speed": "0", "vehicle_lat": "42.3046875", "vehicle_bearing": "4", "vehicle_timestamp": "1512531442", "vehicle_label": "1640", "vehicle_id": "y1640"}}, {"pre_away": "1772", "trip_id": "35272399", "pre_dt": "1512533290", "sch_dep_dt": "1512533280", "sch_arr_dt": "1512533280", "trip_name": "10:48 pm from Forest Hills Station to Back Bay Station", "trip_headsign": "Back Bay"}, {"pre_away": "3174", "trip_id": "35272378", "pre_dt": "1512534692", "sch_dep_dt": "1512534540", "sch_arr_dt": "1512534540", "trip_name": "11:12 pm from Forest Hills Station to Back Bay Station", "trip_headsign": "Back Bay"}, {"pre_away": "4614", "trip_id": "35272363", "pre_dt": "1512536132", "sch_dep_dt": "1512535980", "sch_arr_dt": "1512535980", "trip_name": "11:36 pm from Forest Hills Station to Back Bay Station", "trip_headsign": "Back Bay"}], "time": 1512531524.902643}, "3845": {"info": [{"pre_away": "968", "trip_id": "35272360", "pre_dt": "1512532516", "sch_dep_dt": "1512532680", "sch_arr_dt": "1512532680", "trip_name": "10:36 pm from Forest Hills Station to Back Bay Station", "trip_headsign": "Back Bay", "vehicle": {"vehicle_lon": "-71.1154861450195", "vehicle_speed": "0", "vehicle_lat": "42.3074836730957", "vehicle_bearing": "355", "vehicle_timestamp": "1512531502", "vehicle_label": "1640", "vehicle_id": "y1640"}}, {"pre_away": "1723", "trip_id": "35272399", "pre_dt": "1512533271", "sch_dep_dt": "1512533280", "sch_arr_dt": "1512533280", "trip_name": "10:48 pm from Forest Hills Station to Back Bay Station", "trip_headsign": "Back Bay"}, {"pre_away": "3144", "trip_id": "35272378", "pre_dt": "1512534692", "sch_dep_dt": "1512534540", "sch_arr_dt": "1512534540", "trip_name": "11:12 pm from Forest Hills Station to Back Bay Station", "trip_headsign": "Back Bay"}, {"pre_away": "4584", "trip_id": "35272363", "pre_dt": "1512536132", "sch_dep_dt": "1512535980", "sch_arr_dt": "1512535980", "trip_name": "11:36 pm from Forest Hills Station to Back Bay Station", "trip_headsign": "Back Bay"}], "time": 1512531555.151024}, "3846": {"info": [{"pre_away": "938", "trip_id": "35272360", "pre_dt": "1512532516", "sch_dep_dt": "1512532680", "sch_arr_dt": "1512532680", "trip_name": "10:36 pm from Forest Hills Station to Back Bay Station", "trip_headsign": "Back Bay", "vehicle": {"vehicle_lon": "-71.1155242919922", "vehicle_speed": "0", "vehicle_lat": "42.3095893859863", "vehicle_bearing": "90", "vehicle_timestamp": "1512531556", "vehicle_label": "1640", "vehicle_id": "y1640"}}, {"pre_away": "1693", "trip_id": "35272399", "pre_dt": "1512533271", "sch_dep_dt": "1512533280", "sch_arr_dt": "1512533280", "trip_name": "10:48 pm from Forest Hills Station to Back Bay Station", "trip_headsign": "Back Bay"}, {"pre_away": "3114", "trip_id": "35272378", "pre_dt": "1512534692", "sch_dep_dt": "1512534540", "sch_arr_dt": "1512534540", "trip_name": "11:12 pm from Forest Hills Station to Back Bay Station", "trip_headsign": "Back Bay"}, {"pre_away": "4554", "trip_id": "35272363", "pre_dt": "1512536132", "sch_dep_dt": "1512535980", "sch_arr_dt": "1512535980", "trip_name": "11:36 pm from Forest Hills Station to Back Bay Station", "trip_headsign": "Back Bay"}], "time": 1512531585.448455}, "3847": {"info": [{"pre_away": "945", "trip_id": "35272360", "pre_dt": "1512532554", "sch_dep_dt": "1512532680", "sch_arr_dt": "1512532680", "trip_name": "10:36 pm from Forest Hills Station to Back Bay Station", "trip_headsign": "Back Bay", "vehicle": {"vehicle_lon": "-71.1155242919922", "vehicle_speed": "0", "vehicle_lat": "42.3095893859863", "vehicle_bearing": "90", "vehicle_timestamp": "1512531556", "vehicle_label": "1640", "vehicle_id": "y1640"}}, {"pre_away": "1695", "trip_id": "35272399", "pre_dt": "1512533304", "sch_dep_dt": "1512533280", "sch_arr_dt": "1512533280", "trip_name": "10:48 pm from Forest Hills Station to Back Bay Station", "trip_headsign": "Back Bay"}, {"pre_away": "3083", "trip_id": "35272378", "pre_dt": "1512534692", "sch_dep_dt": "1512534540", "sch_arr_dt": "1512534540", "trip_name": "11:12 pm from Forest Hills Station to Back Bay Station", "trip_headsign": "Back Bay"}, {"pre_away": "4523", "trip_id": "35272363", "pre_dt": "1512536132", "sch_dep_dt": "1512535980", "sch_arr_dt": "1512535980", "trip_name": "11:36 pm from Forest Hills Station to Back Bay Station", "trip_headsign": "Back Bay"}], "time": 1512531615.659314}, "3848": {"info": [{"pre_away": "921", "trip_id": "35272360", "pre_dt": "1512532560", "sch_dep_dt": "1512532680", "sch_arr_dt": "1512532680", "trip_name": "10:36 pm from Forest Hills Station to Back Bay Station", "trip_headsign": "Back Bay", "vehicle": {"vehicle_lon": "-71.1155242919922", "vehicle_speed": "0", "vehicle_lat": "42.3095893859863", "vehicle_bearing": "90", "vehicle_timestamp": "1512531556", "vehicle_label": "1640", "vehicle_id": "y1640"}}, {"pre_away": "1658", "trip_id": "35272399", "pre_dt": "1512533297", "sch_dep_dt": "1512533280", "sch_arr_dt": "1512533280", "trip_name": "10:48 pm from Forest Hills Station to Back Bay Station", "trip_headsign": "Back Bay"}, {"pre_away": "3053", "trip_id": "35272378", "pre_dt": "1512534692", "sch_dep_dt": "1512534540", "sch_arr_dt": "1512534540", "trip_name": "11:12 pm from Forest Hills Station to Back Bay Station", "trip_headsign": "Back Bay"}, {"pre_away": "4493", "trip_id": "35272363", "pre_dt": "1512536132", "sch_dep_dt": "1512535980", "sch_arr_dt": "1512535980", "trip_name": "11:36 pm from Forest Hills Station to Back Bay Station", "trip_headsign": "Back Bay"}], "time": 1512531645.804914}, "3849": {"info": [{"pre_away": "891", "trip_id": "35272360", "pre_dt": "1512532560", "sch_dep_dt": "1512532680", "sch_arr_dt": "1512532680", "trip_name": "10:36 pm from Forest Hills Station to Back Bay Station", "trip_headsign": "Back Bay", "vehicle": {"vehicle_lon": "-71.114143371582", "vehicle_speed": "0", "vehicle_lat": "42.3126564025879", "vehicle_bearing": "4", "vehicle_timestamp": "1512531616", "vehicle_label": "1640", "vehicle_id": "y1640"}}, {"pre_away": "1628", "trip_id": "35272399", "pre_dt": "1512533297", "sch_dep_dt": "1512533280", "sch_arr_dt": "1512533280", "trip_name": "10:48 pm from Forest Hills Station to Back Bay Station", "trip_headsign": "Back Bay"}, {"pre_away": "3023", "trip_id": "35272378", "pre_dt": "1512534692", "sch_dep_dt": "1512534540", "sch_arr_dt": "1512534540", "trip_name": "11:12 pm from Forest Hills Station to Back Bay Station", "trip_headsign": "Back Bay"}, {"pre_away": "4463", "trip_id": "35272363", "pre_dt": "1512536132", "sch_dep_dt": "1512535980", "sch_arr_dt": "1512535980", "trip_name": "11:36 pm from Forest Hills Station to Back Bay Station", "trip_headsign": "Back Bay"}], "time": 1512531675.956617}, "3800": {"info": [{"pre_away": "791", "trip_id": "35272387", "pre_dt": "1512530981", "sch_dep_dt": "1512530520", "sch_arr_dt": "1512530520", "trip_name": "10:00 pm from Forest Hills Station to Back Bay Station", "trip_headsign": "Back Bay", "vehicle": {"vehicle_lon": "-71.1116180419922", "vehicle_speed": "0", "vehicle_lat": "42.3199577331543", "vehicle_bearing": "350", "vehicle_timestamp": "1512530144", "vehicle_label": "1621", "vehicle_id": "y1621"}}, {"pre_away": "868", "trip_id": "35272376", "pre_dt": "1512531058", "sch_dep_dt": "1512531240", "sch_arr_dt": "1512531240", "trip_name": "10:12 pm from Forest Hills Station to Back Bay Station", "trip_headsign": "Back Bay", "vehicle": {"vehicle_lon": "-71.1140060424805", "vehicle_speed": "0", "vehicle_lat": "42.3133239746094", "vehicle_bearing": "2", "vehicle_timestamp": "1512530122", "vehicle_label": "1642", "vehicle_id": "y1642"}}, {"pre_away": "2342", "trip_id": "35272360", "pre_dt": "1512532532", "sch_dep_dt": "1512532680", "sch_arr_dt": "1512532680", "trip_name": "10:36 pm from Forest Hills Station to Back Bay Station", "trip_headsign": "Back Bay"}, {"pre_away": "3062", "trip_id": "35272399", "pre_dt": "1512533252", "sch_dep_dt": "1512533280", "sch_arr_dt": "1512533280", "trip_name": "10:48 pm from Forest Hills Station to Back Bay Station", "trip_headsign": "Back Bay"}, {"pre_away": "4502", "trip_id": "35272378", "pre_dt": "1512534692", "sch_dep_dt": "1512534540", "sch_arr_dt": "1512534540", "trip_name": "11:12 pm from Forest Hills Station to Back Bay Station", "trip_headsign": "Back Bay"}], "time": 1512530195.339963}, "3801": {"info": [{"pre_away": "761", "trip_id": "35272387", "pre_dt": "1512530981", "sch_dep_dt": "1512530520", "sch_arr_dt": "1512530520", "trip_name": "10:00 pm from Forest Hills Station to Back Bay Station", "trip_headsign": "Back Bay", "vehicle": {"vehicle_lon": "-71.1116180419922", "vehicle_speed": "0", "vehicle_lat": "42.3199577331543", "vehicle_bearing": "350", "vehicle_timestamp": "1512530144", "vehicle_label": "1621", "vehicle_id": "y1621"}}, {"pre_away": "838", "trip_id": "35272376", "pre_dt": "1512531058", "sch_dep_dt": "1512531240", "sch_arr_dt": "1512531240", "trip_name": "10:12 pm from Forest Hills Station to Back Bay Station", "trip_headsign": "Back Bay", "vehicle": {"vehicle_lon": "-71.1140060424805", "vehicle_speed": "0", "vehicle_lat": "42.3133239746094", "vehicle_bearing": "2", "vehicle_timestamp": "1512530122", "vehicle_label": "1642", "vehicle_id": "y1642"}}, {"pre_away": "2312", "trip_id": "35272360", "pre_dt": "1512532532", "sch_dep_dt": "1512532680", "sch_arr_dt": "1512532680", "trip_name": "10:36 pm from Forest Hills Station to Back Bay Station", "trip_headsign": "Back Bay"}, {"pre_away": "3032", "trip_id": "35272399", "pre_dt": "1512533252", "sch_dep_dt": "1512533280", "sch_arr_dt": "1512533280", "trip_name": "10:48 pm from Forest Hills Station to Back Bay Station", "trip_headsign": "Back Bay"}, {"pre_away": "4472", "trip_id": "35272378", "pre_dt": "1512534692", "sch_dep_dt": "1512534540", "sch_arr_dt": "1512534540", "trip_name": "11:12 pm from Forest Hills Station to Back Bay Station", "trip_headsign": "Back Bay"}], "time": 1512530225.579882}, "3802": {"info": [{"pre_away": "730", "trip_id": "35272387", "pre_dt": "1512530980", "sch_dep_dt": "1512530520", "sch_arr_dt": "1512530520", "trip_name": "10:00 pm from Forest Hills Station to Back Bay Station", "trip_headsign": "Back Bay", "vehicle": {"vehicle_lon": "-71.1122436523438", "vehicle_speed": "0", "vehicle_lat": "42.3241539001465", "vehicle_bearing": "353", "vehicle_timestamp": "1512530208", "vehicle_label": "1621", "vehicle_id": "y1621"}}, {"pre_away": "820", "trip_id": "35272376", "pre_dt": "1512531070", "sch_dep_dt": "1512531240", "sch_arr_dt": "1512531240", "trip_name": "10:12 pm from Forest Hills Station to Back Bay Station", "trip_headsign": "Back Bay", "vehicle": {"vehicle_lon": "-71.1133346557617", "vehicle_speed": "0", "vehicle_lat": "42.3169937133789", "vehicle_bearing": "4", "vehicle_timestamp": "1512530182", "vehicle_label": "1642", "vehicle_id": "y1642"}}, {"pre_away": "2282", "trip_id": "35272360", "pre_dt": "1512532532", "sch_dep_dt": "1512532680", "sch_arr_dt": "1512532680", "trip_name": "10:36 pm from Forest Hills Station to Back Bay Station", "trip_headsign": "Back Bay"}, {"pre_away": "3002", "trip_id": "35272399", "pre_dt": "1512533252", "sch_dep_dt": "1512533280", "sch_arr_dt": "1512533280", "trip_name": "10:48 pm from Forest Hills Station to Back Bay Station", "trip_headsign": "Back Bay"}, {"pre_away": "4442", "trip_id": "35272378", "pre_dt": "1512534692", "sch_dep_dt": "1512534540", "sch_arr_dt": "1512534540", "trip_name": "11:12 pm from Forest Hills Station to Back Bay Station", "trip_headsign": "Back Bay"}], "time": 1512530255.732912}, "3803": {"info": [{"pre_away": "700", "trip_id": "35272387", "pre_dt": "1512530980", "sch_dep_dt": "1512530520", "sch_arr_dt": "1512530520", "trip_name": "10:00 pm from Forest Hills Station to Back Bay Station", "trip_headsign": "Back Bay", "vehicle": {"vehicle_lon": "-71.1122436523438", "vehicle_speed": "0", "vehicle_lat": "42.3241539001465", "vehicle_bearing": "353", "vehicle_timestamp": "1512530208", "vehicle_label": "1621", "vehicle_id": "y1621"}}, {"pre_away": "790", "trip_id": "35272376", "pre_dt": "1512531070", "sch_dep_dt": "1512531240", "sch_arr_dt": "1512531240", "trip_name": "10:12 pm from Forest Hills Station to Back Bay Station", "trip_headsign": "Back Bay", "vehicle": {"vehicle_lon": "-71.1133346557617", "vehicle_speed": "0", "vehicle_lat": "42.3169937133789", "vehicle_bearing": "4", "vehicle_timestamp": "1512530182", "vehicle_label": "1642", "vehicle_id": "y1642"}}, {"pre_away": "2252", "trip_id": "35272360", "pre_dt": "1512532532", "sch_dep_dt": "1512532680", "sch_arr_dt": "1512532680", "trip_name": "10:36 pm from Forest Hills Station to Back Bay Station", "trip_headsign": "Back Bay"}, {"pre_away": "2972", "trip_id": "35272399", "pre_dt": "1512533252", "sch_dep_dt": "1512533280", "sch_arr_dt": "1512533280", "trip_name": "10:48 pm from Forest Hills Station to Back Bay Station", "trip_headsign": "Back Bay"}, {"pre_away": "4412", "trip_id": "35272378", "pre_dt": "1512534692", "sch_dep_dt": "1512534540", "sch_arr_dt": "1512534540", "trip_name": "11:12 pm from Forest Hills Station to Back Bay Station", "trip_headsign": "Back Bay"}], "time": 1512530285.882896}, "3804": {"info": [{"pre_away": "676", "trip_id": "35272387", "pre_dt": "1512530986", "sch_dep_dt": "1512530520", "sch_arr_dt": "1512530520", "trip_name": "10:00 pm from Forest Hills Station to Back Bay Station", "trip_headsign": "Back Bay", "vehicle": {"vehicle_lon": "-71.110710144043", "vehicle_speed": "0", "vehicle_lat": "42.3289260864258", "vehicle_bearing": "66", "vehicle_timestamp": "1512530263", "vehicle_label": "1621", "vehicle_id": "y1621"}}, {"pre_away": "789", "trip_id": "35272376", "pre_dt": "1512531099", "sch_dep_dt": "1512531240", "sch_arr_dt": "1512531240", "trip_name": "10:12 pm from Forest Hills Station to Back Bay Station", "trip_headsign": "Back Bay", "vehicle": {"vehicle_lon": "-71.1116104125977", "vehicle_speed": "0", "vehicle_lat": "42.3198204040527", "vehicle_bearing": "352", "vehicle_timestamp": "1512530260", "vehicle_label": "1642", "vehicle_id": "y1642"}}, {"pre_away": "2222", "trip_id": "35272360", "pre_dt": "1512532532", "sch_dep_dt": "1512532680", "sch_arr_dt": "1512532680", "trip_name": "10:36 pm from Forest Hills Station to Back Bay Station", "trip_headsign": "Back Bay"}, {"pre_away": "2942", "trip_id": "35272399", "pre_dt": "1512533252", "sch_dep_dt": "1512533280", "sch_arr_dt": "1512533280", "trip_name": "10:48 pm from Forest Hills Station to Back Bay Station", "trip_headsign": "Back Bay"}, {"pre_away": "4382", "trip_id": "35272378", "pre_dt": "1512534692", "sch_dep_dt": "1512534540", "sch_arr_dt": "1512534540", "trip_name": "11:12 pm from Forest Hills Station to Back Bay Station", "trip_headsign": "Back Bay"}], "time": 1512530316.029122}, "3805": {"info": [{"pre_away": "645", "trip_id": "35272387", "pre_dt": "1512530986", "sch_dep_dt": "1512530520", "sch_arr_dt": "1512530520", "trip_name": "10:00 pm from Forest Hills Station to Back Bay Station", "trip_headsign": "Back Bay", "vehicle": {"vehicle_lon": "-71.110710144043", "vehicle_speed": "0", "vehicle_lat": "42.3289260864258", "vehicle_bearing": "66", "vehicle_timestamp": "1512530263", "vehicle_label": "1621", "vehicle_id": "y1621"}}, {"pre_away": "758", "trip_id": "35272376", "pre_dt": "1512531099", "sch_dep_dt": "1512531240", "sch_arr_dt": "1512531240", "trip_name": "10:12 pm from Forest Hills Station to Back Bay Station", "trip_headsign": "Back Bay", "vehicle": {"vehicle_lon": "-71.1116104125977", "vehicle_speed": "0", "vehicle_lat": "42.3198204040527", "vehicle_bearing": "352", "vehicle_timestamp": "1512530260", "vehicle_label": "1642", "vehicle_id": "y1642"}}, {"pre_away": "2191", "trip_id": "35272360", "pre_dt": "1512532532", "sch_dep_dt": "1512532680", "sch_arr_dt": "1512532680", "trip_name": "10:36 pm from Forest Hills Station to Back Bay Station", "trip_headsign": "Back Bay"}, {"pre_away": "2911", "trip_id": "35272399", "pre_dt": "1512533252", "sch_dep_dt": "1512533280", "sch_arr_dt": "1512533280", "trip_name": "10:48 pm from Forest Hills Station to Back Bay Station", "trip_headsign": "Back Bay"}, {"pre_away": "4351", "trip_id": "35272378", "pre_dt": "1512534692", "sch_dep_dt": "1512534540", "sch_arr_dt": "1512534540", "trip_name": "11:12 pm from Forest Hills Station to Back Bay Station", "trip_headsign": "Back Bay"}], "time": 1512530346.18557}, "3806": {"info": [{"pre_away": "631", "trip_id": "35272387", "pre_dt": "1512531002", "sch_dep_dt": "1512530520", "sch_arr_dt": "1512530520", "trip_name": "10:00 pm from Forest Hills Station to Back Bay Station", "trip_headsign": "Back Bay", "vehicle": {"vehicle_lon": "-71.1117630004883", "vehicle_speed": "0", "vehicle_lat": "42.3313522338867", "vehicle_bearing": "344", "vehicle_timestamp": "1512530324", "vehicle_label": "1621", "vehicle_id": "y1621"}}, {"pre_away": "752", "trip_id": "35272376", "pre_dt": "1512531123", "sch_dep_dt": "1512531240", "sch_arr_dt": "1512531240", "trip_name": "10:12 pm from Forest Hills Station to Back Bay Station", "trip_headsign": "Back Bay", "vehicle": {"vehicle_lon": "-71.1120071411133", "vehicle_speed": "0", "vehicle_lat": "42.3218116760254", "vehicle_bearing": "348", "vehicle_timestamp": "1512530321", "vehicle_label": "1642", "vehicle_id": "y1642"}}, {"pre_away": "2161", "trip_id": "35272360", "pre_dt": "1512532532", "sch_dep_dt": "1512532680", "sch_arr_dt": "1512532680", "trip_name": "10:36 pm from Forest Hills Station to Back Bay Station", "trip_headsign": "Back Bay"}, {"pre_away": "2881", "trip_id": "35272399", "pre_dt": "1512533252", "sch_dep_dt": "1512533280", "sch_arr_dt": "1512533280", "trip_name": "10:48 pm from Forest Hills Station to Back Bay Station", "trip_headsign": "Back Bay"}, {"pre_away": "4321", "trip_id": "35272378", "pre_dt": "1512534692", "sch_dep_dt": "1512534540", "sch_arr_dt": "1512534540", "trip_name": "11:12 pm from Forest Hills Station to Back Bay Station", "trip_headsign": "Back Bay"}], "time": 1512530376.41814}, "3807": {"info": [{"pre_away": "601", "trip_id": "35272387", "pre_dt": "1512531002", "sch_dep_dt": "1512530520", "sch_arr_dt": "1512530520", "trip_name": "10:00 pm from Forest Hills Station to Back Bay Station", "trip_headsign": "Back Bay", "vehicle": {"vehicle_lon": "-71.1117630004883", "vehicle_speed": "0", "vehicle_lat": "42.3313522338867", "vehicle_bearing": "344", "vehicle_timestamp": "1512530324", "vehicle_label": "1621", "vehicle_id": "y1621"}}, {"pre_away": "722", "trip_id": "35272376", "pre_dt": "1512531123", "sch_dep_dt": "1512531240", "sch_arr_dt": "1512531240", "trip_name": "10:12 pm from Forest Hills Station to Back Bay Station", "trip_headsign": "Back Bay", "vehicle": {"vehicle_lon": "-71.1120071411133", "vehicle_speed": "0", "vehicle_lat": "42.3218116760254", "vehicle_bearing": "348", "vehicle_timestamp": "1512530321", "vehicle_label": "1642", "vehicle_id": "y1642"}}, {"pre_away": "2131", "trip_id": "35272360", "pre_dt": "1512532532", "sch_dep_dt": "1512532680", "sch_arr_dt": "1512532680", "trip_name": "10:36 pm from Forest Hills Station to Back Bay Station", "trip_headsign": "Back Bay"}, {"pre_away": "2851", "trip_id": "35272399", "pre_dt": "1512533252", "sch_dep_dt": "1512533280", "sch_arr_dt": "1512533280", "trip_name": "10:48 pm from Forest Hills Station to Back Bay Station", "trip_headsign": "Back Bay"}, {"pre_away": "4291", "trip_id": "35272378", "pre_dt": "1512534692", "sch_dep_dt": "1512534540", "sch_arr_dt": "1512534540", "trip_name": "11:12 pm from Forest Hills Station to Back Bay Station", "trip_headsign": "Back Bay"}], "time": 1512530406.831756}, "3808": {"info": [{"pre_away": "621", "trip_id": "35272387", "pre_dt": "1512531052", "sch_dep_dt": "1512530520", "sch_arr_dt": "1512530520", "trip_name": "10:00 pm from Forest Hills Station to Back Bay Station", "trip_headsign": "Back Bay", "vehicle": {"vehicle_lon": "-71.111946105957", "vehicle_speed": "0", "vehicle_lat": "42.3318328857422", "vehicle_bearing": "75", "vehicle_timestamp": "1512530384", "vehicle_label": "1621", "vehicle_id": "y1621"}}, {"pre_away": "692", "trip_id": "35272376", "pre_dt": "1512531123", "sch_dep_dt": "1512531240", "sch_arr_dt": "1512531240", "trip_name": "10:12 pm from Forest Hills Station to Back Bay Station", "trip_headsign": "Back Bay", "vehicle": {"vehicle_lon": "-71.1120071411133", "vehicle_speed": "0", "vehicle_lat": "42.3218116760254", "vehicle_bearing": "348", "vehicle_timestamp": "1512530321", "vehicle_label": "1642", "vehicle_id": "y1642"}}, {"pre_away": "2101", "trip_id": "35272360", "pre_dt": "1512532532", "sch_dep_dt": "1512532680", "sch_arr_dt": "1512532680", "trip_name": "10:36 pm from Forest Hills Station to Back Bay Station", "trip_headsign": "Back Bay"}, {"pre_away": "2821", "trip_id": "35272399", "pre_dt": "1512533252", "sch_dep_dt": "1512533280", "sch_arr_dt": "1512533280", "trip_name": "10:48 pm from Forest Hills Station to Back Bay Station", "trip_headsign": "Back Bay"}, {"pre_away": "4261", "trip_id": "35272378", "pre_dt": "1512534692", "sch_dep_dt": "1512534540", "sch_arr_dt": "1512534540", "trip_name": "11:12 pm from Forest Hills Station to Back Bay Station", "trip_headsign": "Back Bay"}], "time": 1512530437.101216}, "3809": {"info": [{"pre_away": "591", "trip_id": "35272387", "pre_dt": "1512531052", "sch_dep_dt": "1512530520", "sch_arr_dt": "1512530520", "trip_name": "10:00 pm from Forest Hills Station to Back Bay Station", "trip_headsign": "Back Bay", "vehicle": {"vehicle_lon": "-71.111946105957", "vehicle_speed": "0", "vehicle_lat": "42.3318328857422", "vehicle_bearing": "75", "vehicle_timestamp": "1512530384", "vehicle_label": "1621", "vehicle_id": "y1621"}}, {"pre_away": "662", "trip_id": "35272376", "pre_dt": "1512531123", "sch_dep_dt": "1512531240", "sch_arr_dt": "1512531240", "trip_name": "10:12 pm from Forest Hills Station to Back Bay Station", "trip_headsign": "Back Bay", "vehicle": {"vehicle_lon": "-71.1107559204102", "vehicle_speed": "0", "vehicle_lat": "42.3290557861328", "vehicle_bearing": "345", "vehicle_timestamp": "1512530427", "vehicle_label": "1642", "vehicle_id": "y1642"}}, {"pre_away": "2071", "trip_id": "35272360", "pre_dt": "1512532532", "sch_dep_dt": "1512532680", "sch_arr_dt": "1512532680", "trip_name": "10:36 pm from Forest Hills Station to Back Bay Station", "trip_headsign": "Back Bay"}, {"pre_away": "2791", "trip_id": "35272399", "pre_dt": "1512533252", "sch_dep_dt": "1512533280", "sch_arr_dt": "1512533280", "trip_name": "10:48 pm from Forest Hills Station to Back Bay Station", "trip_headsign": "Back Bay"}, {"pre_away": "4231", "trip_id": "35272378", "pre_dt": "1512534692", "sch_dep_dt": "1512534540", "sch_arr_dt": "1512534540", "trip_name": "11:12 pm from Forest Hills Station to Back Bay Station", "trip_headsign": "Back Bay"}], "time": 1512530467.248025}, "3810": {"info": [{"pre_away": "594", "trip_id": "35272387", "pre_dt": "1512531085", "sch_dep_dt": "1512530520", "sch_arr_dt": "1512530520", "trip_name": "10:00 pm from Forest Hills Station to Back Bay Station", "trip_headsign": "Back Bay", "vehicle": {"vehicle_lon": "-71.1107177734375", "vehicle_speed": "0", "vehicle_lat": "42.3327827453613", "vehicle_bearing": "54", "vehicle_timestamp": "1512530444", "vehicle_label": "1621", "vehicle_id": "y1621"}}, {"pre_away": "654", "trip_id": "35272376", "pre_dt": "1512531145", "sch_dep_dt": "1512531240", "sch_arr_dt": "1512531240", "trip_name": "10:12 pm from Forest Hills Station to Back Bay Station", "trip_headsign": "Back Bay", "vehicle": {"vehicle_lon": "-71.1107559204102", "vehicle_speed": "0", "vehicle_lat": "42.3290557861328", "vehicle_bearing": "345", "vehicle_timestamp": "1512530427", "vehicle_label": "1642", "vehicle_id": "y1642"}}, {"pre_away": "2041", "trip_id": "35272360", "pre_dt": "1512532532", "sch_dep_dt": "1512532680", "sch_arr_dt": "1512532680", "trip_name": "10:36 pm from Forest Hills Station to Back Bay Station", "trip_headsign": "Back Bay"}, {"pre_away": "2761", "trip_id": "35272399", "pre_dt": "1512533252", "sch_dep_dt": "1512533280", "sch_arr_dt": "1512533280", "trip_name": "10:48 pm from Forest Hills Station to Back Bay Station", "trip_headsign": "Back Bay"}, {"pre_away": "4201", "trip_id": "35272378", "pre_dt": "1512534692", "sch_dep_dt": "1512534540", "sch_arr_dt": "1512534540", "trip_name": "11:12 pm from Forest Hills Station to Back Bay Station", "trip_headsign": "Back Bay"}], "time": 1512530497.389806}, "3811": {"info": [{"pre_away": "563", "trip_id": "35272387", "pre_dt": "1512531085", "sch_dep_dt": "1512530520", "sch_arr_dt": "1512530520", "trip_name": "10:00 pm from Forest Hills Station to Back Bay Station", "trip_headsign": "Back Bay", "vehicle": {"vehicle_lon": "-71.1107177734375", "vehicle_speed": "0", "vehicle_lat": "42.3327827453613", "vehicle_bearing": "54", "vehicle_timestamp": "1512530444", "vehicle_label": "1621", "vehicle_id": "y1621"}}, {"pre_away": "633", "trip_id": "35272376", "pre_dt": "1512531155", "sch_dep_dt": "1512531240", "sch_arr_dt": "1512531240", "trip_name": "10:12 pm from Forest Hills Station to Back Bay Station", "trip_headsign": "Back Bay", "vehicle": {"vehicle_lon": "-71.111930847168", "vehicle_speed": "0", "vehicle_lat": "42.3318367004395", "vehicle_bearing": "75", "vehicle_timestamp": "1512530487", "vehicle_label": "1642", "vehicle_id": "y1642"}}, {"pre_away": "2010", "trip_id": "35272360", "pre_dt": "1512532532", "sch_dep_dt": "1512532680", "sch_arr_dt": "1512532680", "trip_name": "10:36 pm from Forest Hills Station to Back Bay Station", "trip_headsign": "Back Bay"}, {"pre_away": "2730", "trip_id": "35272399", "pre_dt": "1512533252", "sch_dep_dt": "1512533280", "sch_arr_dt": "1512533280", "trip_name": "10:48 pm from Forest Hills Station to Back Bay Station", "trip_headsign": "Back Bay"}, {"pre_away": "4170", "trip_id": "35272378", "pre_dt": "1512534692", "sch_dep_dt": "1512534540", "sch_arr_dt": "1512534540", "trip_name": "11:12 pm from Forest Hills Station to Back Bay Station", "trip_headsign": "Back Bay"}], "time": 1512530527.537068}, "3812": {"info": [{"pre_away": "528", "trip_id": "35272387", "pre_dt": "1512531080", "sch_dep_dt": "1512530520", "sch_arr_dt": "1512530520", "trip_name": "10:00 pm from Forest Hills Station to Back Bay Station", "trip_headsign": "Back Bay", "vehicle": {"vehicle_lon": "-71.1055374145508", "vehicle_speed": "0", "vehicle_lat": "42.3337745666504", "vehicle_bearing": "64", "vehicle_timestamp": "1512530509", "vehicle_label": "1621", "vehicle_id": "y1621"}}, {"pre_away": "603", "trip_id": "35272376", "pre_dt": "1512531155", "sch_dep_dt": "1512531240", "sch_arr_dt": "1512531240", "trip_name": "10:12 pm from Forest Hills Station to Back Bay Station", "trip_headsign": "Back Bay", "vehicle": {"vehicle_lon": "-71.111930847168", "vehicle_speed": "0", "vehicle_lat": "42.3318367004395", "vehicle_bearing": "75", "vehicle_timestamp": "1512530487", "vehicle_label": "1642", "vehicle_id": "y1642"}}, {"pre_away": "1980", "trip_id": "35272360", "pre_dt": "1512532532", "sch_dep_dt": "1512532680", "sch_arr_dt": "1512532680", "trip_name": "10:36 pm from Forest Hills Station to Back Bay Station", "trip_headsign": "Back Bay"}, {"pre_away": "2700", "trip_id": "35272399", "pre_dt": "1512533252", "sch_dep_dt": "1512533280", "sch_arr_dt": "1512533280", "trip_name": "10:48 pm from Forest Hills Station to Back Bay Station", "trip_headsign": "Back Bay"}, {"pre_away": "4140", "trip_id": "35272378", "pre_dt": "1512534692", "sch_dep_dt": "1512534540", "sch_arr_dt": "1512534540", "trip_name": "11:12 pm from Forest Hills Station to Back Bay Station", "trip_headsign": "Back Bay"}], "time": 1512530557.879901}, "3813": {"info": [{"pre_away": "498", "trip_id": "35272387", "pre_dt": "1512531080", "sch_dep_dt": "1512530520", "sch_arr_dt": "1512530520", "trip_name": "10:00 pm from Forest Hills Station to Back Bay Station", "trip_headsign": "Back Bay", "vehicle": {"vehicle_lon": "-71.1055374145508", "vehicle_speed": "0", "vehicle_lat": "42.3337745666504", "vehicle_bearing": "64", "vehicle_timestamp": "1512530509", "vehicle_label": "1621", "vehicle_id": "y1621"}}, {"pre_away": "628", "trip_id": "35272376", "pre_dt": "1512531210", "sch_dep_dt": "1512531240", "sch_arr_dt": "1512531240", "trip_name": "10:12 pm from Forest Hills Station to Back Bay Station", "trip_headsign": "Back Bay", "vehicle": {"vehicle_lon": "-71.1119537353516", "vehicle_speed": "0", "vehicle_lat": "42.3318977355957", "vehicle_bearing": "324", "vehicle_timestamp": "1512530543", "vehicle_label": "1642", "vehicle_id": "y1642"}}, {"pre_away": "1950", "trip_id": "35272360", "pre_dt": "1512532532", "sch_dep_dt": "1512532680", "sch_arr_dt": "1512532680", "trip_name": "10:36 pm from Forest Hills Station to Back Bay Station", "trip_headsign": "Back Bay"}, {"pre_away": "2670", "trip_id": "35272399", "pre_dt": "1512533252", "sch_dep_dt": "1512533280", "sch_arr_dt": "1512533280", "trip_name": "10:48 pm from Forest Hills Station to Back Bay Station", "trip_headsign": "Back Bay"}, {"pre_away": "4110", "trip_id": "35272378", "pre_dt": "1512534692", "sch_dep_dt": "1512534540", "sch_arr_dt": "1512534540", "trip_name": "11:12 pm from Forest Hills Station to Back Bay Station", "trip_headsign": "Back Bay"}], "time": 1512530588.090634}, "3814": {"info": [{"pre_away": "486", "trip_id": "35272387", "pre_dt": "1512531098", "sch_dep_dt": "1512530520", "sch_arr_dt": "1512530520", "trip_name": "10:00 pm from Forest Hills Station to Back Bay Station", "trip_headsign": "Back Bay", "vehicle": {"vehicle_lon": "-71.1029434204102", "vehicle_speed": "0", "vehicle_lat": "42.334789276123", "vehicle_bearing": "63", "vehicle_timestamp": "1512530569", "vehicle_label": "1621", "vehicle_id": "y1621"}}, {"pre_away": "598", "trip_id": "35272376", "pre_dt": "1512531210", "sch_dep_dt": "1512531240", "sch_arr_dt": "1512531240", "trip_name": "10:12 pm from Forest Hills Station to Back Bay Station", "trip_headsign": "Back Bay", "vehicle": {"vehicle_lon": "-71.1119537353516", "vehicle_speed": "0", "vehicle_lat": "42.3318977355957", "vehicle_bearing": "324", "vehicle_timestamp": "1512530543", "vehicle_label": "1642", "vehicle_id": "y1642"}}, {"pre_away": "1920", "trip_id": "35272360", "pre_dt": "1512532532", "sch_dep_dt": "1512532680", "sch_arr_dt": "1512532680", "trip_name": "10:36 pm from Forest Hills Station to Back Bay Station", "trip_headsign": "Back Bay"}, {"pre_away": "2640", "trip_id": "35272399", "pre_dt": "1512533252", "sch_dep_dt": "1512533280", "sch_arr_dt": "1512533280", "trip_name": "10:48 pm from Forest Hills Station to Back Bay Station", "trip_headsign": "Back Bay"}, {"pre_away": "4080", "trip_id": "35272378", "pre_dt": "1512534692", "sch_dep_dt": "1512534540", "sch_arr_dt": "1512534540", "trip_name": "11:12 pm from Forest Hills Station to Back Bay Station", "trip_headsign": "Back Bay"}], "time": 1512530618.462784}, "3815": {"info": [{"pre_away": "455", "trip_id": "35272387", "pre_dt": "1512531098", "sch_dep_dt": "1512530520", "sch_arr_dt": "1512530520", "trip_name": "10:00 pm from Forest Hills Station to Back Bay Station", "trip_headsign": "Back Bay", "vehicle": {"vehicle_lon": "-71.1029434204102", "vehicle_speed": "0", "vehicle_lat": "42.334789276123", "vehicle_bearing": "63", "vehicle_timestamp": "1512530569", "vehicle_label": "1621", "vehicle_id": "y1621"}}, {"pre_away": "557", "trip_id": "35272376", "pre_dt": "1512531200", "sch_dep_dt": "1512531240", "sch_arr_dt": "1512531240", "trip_name": "10:12 pm from Forest Hills Station to Back Bay Station", "trip_headsign": "Back Bay", "vehicle": {"vehicle_lon": "-71.107421875", "vehicle_speed": "0", "vehicle_lat": "42.3332214355469", "vehicle_bearing": "89", "vehicle_timestamp": "1512530604", "vehicle_label": "1642", "vehicle_id": "y1642"}}, {"pre_away": "1889", "trip_id": "35272360", "pre_dt": "1512532532", "sch_dep_dt": "1512532680", "sch_arr_dt": "1512532680", "trip_name": "10:36 pm from Forest Hills Station to Back Bay Station", "trip_headsign": "Back Bay"}, {"pre_away": "2609", "trip_id": "35272399", "pre_dt": "1512533252", "sch_dep_dt": "1512533280", "sch_arr_dt": "1512533280", "trip_name": "10:48 pm from Forest Hills Station to Back Bay Station", "trip_headsign": "Back Bay"}, {"pre_away": "4049", "trip_id": "35272378", "pre_dt": "1512534692", "sch_dep_dt": "1512534540", "sch_arr_dt": "1512534540", "trip_name": "11:12 pm from Forest Hills Station to Back Bay Station", "trip_headsign": "Back Bay"}], "time": 1512530648.60935}, "3816": {"info": [{"pre_away": "439", "trip_id": "35272387", "pre_dt": "1512531112", "sch_dep_dt": "1512530520", "sch_arr_dt": "1512530520", "trip_name": "10:00 pm from Forest Hills Station to Back Bay Station", "trip_headsign": "Back Bay", "vehicle": {"vehicle_lon": "-71.0986022949219", "vehicle_speed": "0", "vehicle_lat": "42.3363914489746", "vehicle_bearing": "64", "vehicle_timestamp": "1512530644", "vehicle_label": "1621", "vehicle_id": "y1621"}}, {"pre_away": "527", "trip_id": "35272376", "pre_dt": "1512531200", "sch_dep_dt": "1512531240", "sch_arr_dt": "1512531240", "trip_name": "10:12 pm from Forest Hills Station to Back Bay Station", "trip_headsign": "Back Bay", "vehicle": {"vehicle_lon": "-71.1053771972656", "vehicle_speed": "0", "vehicle_lat": "42.3338432312012", "vehicle_bearing": "64", "vehicle_timestamp": "1512530649", "vehicle_label": "1642", "vehicle_id": "y1642"}}, {"pre_away": "1859", "trip_id": "35272360", "pre_dt": "1512532532", "sch_dep_dt": "1512532680", "sch_arr_dt": "1512532680", "trip_name": "10:36 pm from Forest Hills Station to Back Bay Station", "trip_headsign": "Back Bay"}, {"pre_away": "2579", "trip_id": "35272399", "pre_dt": "1512533252", "sch_dep_dt": "1512533280", "sch_arr_dt": "1512533280", "trip_name": "10:48 pm from Forest Hills Station to Back Bay Station", "trip_headsign": "Back Bay"}, {"pre_away": "4019", "trip_id": "35272378", "pre_dt": "1512534692", "sch_dep_dt": "1512534540", "sch_arr_dt": "1512534540", "trip_name": "11:12 pm from Forest Hills Station to Back Bay Station", "trip_headsign": "Back Bay"}], "time": 1512530678.753913}, "3817": {"info": [{"pre_away": "402", "trip_id": "35272387", "pre_dt": "1512531105", "sch_dep_dt": "1512530520", "sch_arr_dt": "1512530520", "trip_name": "10:00 pm from Forest Hills Station to Back Bay Station", "trip_headsign": "Back Bay", "vehicle": {"vehicle_lon": "-71.0986022949219", "vehicle_speed": "0", "vehicle_lat": "42.3363914489746", "vehicle_bearing": "64", "vehicle_timestamp": "1512530644", "vehicle_label": "1621", "vehicle_id": "y1621"}}, {"pre_away": "515", "trip_id": "35272376", "pre_dt": "1512531218", "sch_dep_dt": "1512531240", "sch_arr_dt": "1512531240", "trip_name": "10:12 pm from Forest Hills Station to Back Bay Station", "trip_headsign": "Back Bay", "vehicle": {"vehicle_lon": "-71.1053771972656", "vehicle_speed": "0", "vehicle_lat": "42.3338432312012", "vehicle_bearing": "64", "vehicle_timestamp": "1512530649", "vehicle_label": "1642", "vehicle_id": "y1642"}}, {"pre_away": "1829", "trip_id": "35272360", "pre_dt": "1512532532", "sch_dep_dt": "1512532680", "sch_arr_dt": "1512532680", "trip_name": "10:36 pm from Forest Hills Station to Back Bay Station", "trip_headsign": "Back Bay"}, {"pre_away": "2549", "trip_id": "35272399", "pre_dt": "1512533252", "sch_dep_dt": "1512533280", "sch_arr_dt": "1512533280", "trip_name": "10:48 pm from Forest Hills Station to Back Bay Station", "trip_headsign": "Back Bay"}, {"pre_away": "3989", "trip_id": "35272378", "pre_dt": "1512534692", "sch_dep_dt": "1512534540", "sch_arr_dt": "1512534540", "trip_name": "11:12 pm from Forest Hills Station to Back Bay Station", "trip_headsign": "Back Bay"}], "time": 1512530708.904152}, "3818": {"info": [{"pre_away": "393", "trip_id": "35272387", "pre_dt": "1512531127", "sch_dep_dt": "1512530520", "sch_arr_dt": "1512530520", "trip_name": "10:00 pm from Forest Hills Station to Back Bay Station", "trip_headsign": "Back Bay", "vehicle": {"vehicle_lon": "-71.0951614379883", "vehicle_speed": "0", "vehicle_lat": "42.3378829956055", "vehicle_bearing": "62", "vehicle_timestamp": "1512530704", "vehicle_label": "1621", "vehicle_id": "y1621"}}, {"pre_away": "465", "trip_id": "35272376", "pre_dt": "1512531199", "sch_dep_dt": "1512531240", "sch_arr_dt": "1512531240", "trip_name": "10:12 pm from Forest Hills Station to Back Bay Station", "trip_headsign": "Back Bay", "vehicle": {"vehicle_lon": "-71.1004104614258", "vehicle_speed": "0", "vehicle_lat": "42.3356628417969", "vehicle_bearing": "60", "vehicle_timestamp": "1512530710", "vehicle_label": "1642", "vehicle_id": "y1642"}}, {"pre_away": "1798", "trip_id": "35272360", "pre_dt": "1512532532", "sch_dep_dt": "1512532680", "sch_arr_dt": "1512532680", "trip_name": "10:36 pm from Forest Hills Station to Back Bay Station", "trip_headsign": "Back Bay"}, {"pre_away": "2518", "trip_id": "35272399", "pre_dt": "1512533252", "sch_dep_dt": "1512533280", "sch_arr_dt": "1512533280", "trip_name": "10:48 pm from Forest Hills Station to Back Bay Station", "trip_headsign": "Back Bay"}, {"pre_away": "3958", "trip_id": "35272378", "pre_dt": "1512534692", "sch_dep_dt": "1512534540", "sch_arr_dt": "1512534540", "trip_name": "11:12 pm from Forest Hills Station to Back Bay Station", "trip_headsign": "Back Bay"}], "time": 1512530739.064164}, "3819": {"info": [{"pre_away": "363", "trip_id": "35272387", "pre_dt": "1512531127", "sch_dep_dt": "1512530520", "sch_arr_dt": "1512530520", "trip_name": "10:00 pm from Forest Hills Station to Back Bay Station", "trip_headsign": "Back Bay", "vehicle": {"vehicle_lon": "-71.0951614379883", "vehicle_speed": "0", "vehicle_lat": "42.3378829956055", "vehicle_bearing": "62", "vehicle_timestamp": "1512530704", "vehicle_label": "1621", "vehicle_id": "y1621"}}, {"pre_away": "435", "trip_id": "35272376", "pre_dt": "1512531199", "sch_dep_dt": "1512531240", "sch_arr_dt": "1512531240", "trip_name": "10:12 pm from Forest Hills Station to Back Bay Station", "trip_headsign": "Back Bay", "vehicle": {"vehicle_lon": "-71.1004104614258", "vehicle_speed": "0", "vehicle_lat": "42.3356628417969", "vehicle_bearing": "60", "vehicle_timestamp": "1512530710", "vehicle_label": "1642", "vehicle_id": "y1642"}}, {"pre_away": "1768", "trip_id": "35272360", "pre_dt": "1512532532", "sch_dep_dt": "1512532680", "sch_arr_dt": "1512532680", "trip_name": "10:36 pm from Forest Hills Station to Back Bay Station", "trip_headsign": "Back Bay"}, {"pre_away": "2488", "trip_id": "35272399", "pre_dt": "1512533252", "sch_dep_dt": "1512533280", "sch_arr_dt": "1512533280", "trip_name": "10:48 pm from Forest Hills Station to Back Bay Station", "trip_headsign": "Back Bay"}, {"pre_away": "3928", "trip_id": "35272378", "pre_dt": "1512534692", "sch_dep_dt": "1512534540", "sch_arr_dt": "1512534540", "trip_name": "11:12 pm from Forest Hills Station to Back Bay Station", "trip_headsign": "Back Bay"}], "time": 1512530769.260753}, "3820": {"info": [{"pre_away": "342", "trip_id": "35272387", "pre_dt": "1512531136", "sch_dep_dt": "1512530520", "sch_arr_dt": "1512530520", "trip_name": "10:00 pm from Forest Hills Station to Back Bay Station", "trip_headsign": "Back Bay", "vehicle": {"vehicle_lon": "-71.090950012207", "vehicle_speed": "0", "vehicle_lat": "42.3395118713379", "vehicle_bearing": "63", "vehicle_timestamp": "1512530764", "vehicle_label": "1621", "vehicle_id": "y1621"}}, {"pre_away": "425", "trip_id": "35272376", "pre_dt": "1512531219", "sch_dep_dt": "1512531240", "sch_arr_dt": "1512531240", "trip_name": "10:12 pm from Forest Hills Station to Back Bay Station", "trip_headsign": "Back Bay", "vehicle": {"vehicle_lon": "-71.0987091064453", "vehicle_speed": "0", "vehicle_lat": "42.3363571166992", "vehicle_bearing": "64", "vehicle_timestamp": "1512530757", "vehicle_label": "1642", "vehicle_id": "y1642"}}, {"pre_away": "1738", "trip_id": "35272360", "pre_dt": "1512532532", "sch_dep_dt": "1512532680", "sch_arr_dt": "1512532680", "trip_name": "10:36 pm from Forest Hills Station to Back Bay Station", "trip_headsign": "Back Bay"}, {"pre_away": "2458", "trip_id": "35272399", "pre_dt": "1512533252", "sch_dep_dt": "1512533280", "sch_arr_dt": "1512533280", "trip_name": "10:48 pm from Forest Hills Station to Back Bay Station", "trip_headsign": "Back Bay"}, {"pre_away": "3898", "trip_id": "35272378", "pre_dt": "1512534692", "sch_dep_dt": "1512534540", "sch_arr_dt": "1512534540", "trip_name": "11:12 pm from Forest Hills Station to Back Bay Station", "trip_headsign": "Back Bay"}], "time": 1512530799.591584}, "3821": {"info": [{"pre_away": "312", "trip_id": "35272387", "pre_dt": "1512531136", "sch_dep_dt": "1512530520", "sch_arr_dt": "1512530520", "trip_name": "10:00 pm from Forest Hills Station to Back Bay Station", "trip_headsign": "Back Bay", "vehicle": {"vehicle_lon": "-71.090950012207", "vehicle_speed": "0", "vehicle_lat": "42.3395118713379", "vehicle_bearing": "63", "vehicle_timestamp": "1512530764", "vehicle_label": "1621", "vehicle_id": "y1621"}}, {"pre_away": "395", "trip_id": "35272376", "pre_dt": "1512531219", "sch_dep_dt": "1512531240", "sch_arr_dt": "1512531240", "trip_name": "10:12 pm from Forest Hills Station to Back Bay Station", "trip_headsign": "Back Bay", "vehicle": {"vehicle_lon": "-71.0987091064453", "vehicle_speed": "0", "vehicle_lat": "42.3363571166992", "vehicle_bearing": "64", "vehicle_timestamp": "1512530757", "vehicle_label": "1642", "vehicle_id": "y1642"}}, {"pre_away": "1708", "trip_id": "35272360", "pre_dt": "1512532532", "sch_dep_dt": "1512532680", "sch_arr_dt": "1512532680", "trip_name": "10:36 pm from Forest Hills Station to Back Bay Station", "trip_headsign": "Back Bay"}, {"pre_away": "2428", "trip_id": "35272399", "pre_dt": "1512533252", "sch_dep_dt": "1512533280", "sch_arr_dt": "1512533280", "trip_name": "10:48 pm from Forest Hills Station to Back Bay Station", "trip_headsign": "Back Bay"}, {"pre_away": "3868", "trip_id": "35272378", "pre_dt": "1512534692", "sch_dep_dt": "1512534540", "sch_arr_dt": "1512534540", "trip_name": "11:12 pm from Forest Hills Station to Back Bay Station", "trip_headsign": "Back Bay"}], "time": 1512530829.730435}, "3822": {"info": [{"pre_away": "309", "trip_id": "35272387", "pre_dt": "1512531163", "sch_dep_dt": "1512530520", "sch_arr_dt": "1512530520", "trip_name": "10:00 pm from Forest Hills Station to Back Bay Station", "trip_headsign": "Back Bay", "vehicle": {"vehicle_lon": "-71.0883102416992", "vehicle_speed": "0", "vehicle_lat": "42.340576171875", "vehicle_bearing": "63", "vehicle_timestamp": "1512530822", "vehicle_label": "1621", "vehicle_id": "y1621"}}, {"pre_away": "348", "trip_id": "35272376", "pre_dt": "1512531202", "sch_dep_dt": "1512531240", "sch_arr_dt": "1512531240", "trip_name": "10:12 pm from Forest Hills Station to Back Bay Station", "trip_headsign": "Back Bay", "vehicle": {"vehicle_lon": "-71.0919570922852", "vehicle_speed": "0", "vehicle_lat": "42.339038848877", "vehicle_bearing": "63", "vehicle_timestamp": "1512530817", "vehicle_label": "1642", "vehicle_id": "y1642"}}, {"pre_away": "1678", "trip_id": "35272360", "pre_dt": "1512532532", "sch_dep_dt": "1512532680", "sch_arr_dt": "1512532680", "trip_name": "10:36 pm from Forest Hills Station to Back Bay Station", "trip_headsign": "Back Bay"}, {"pre_away": "2398", "trip_id": "35272399", "pre_dt": "1512533252", "sch_dep_dt": "1512533280", "sch_arr_dt": "1512533280", "trip_name": "10:48 pm from Forest Hills Station to Back Bay Station", "trip_headsign": "Back Bay"}, {"pre_away": "3838", "trip_id": "35272378", "pre_dt": "1512534692", "sch_dep_dt": "1512534540", "sch_arr_dt": "1512534540", "trip_name": "11:12 pm from Forest Hills Station to Back Bay Station", "trip_headsign": "Back Bay"}], "time": 1512530859.877854}, "3823": {"info": [{"pre_away": "278", "trip_id": "35272387", "pre_dt": "1512531163", "sch_dep_dt": "1512530520", "sch_arr_dt": "1512530520", "trip_name": "10:00 pm from Forest Hills Station to Back Bay Station", "trip_headsign": "Back Bay", "vehicle": {"vehicle_lon": "-71.0883102416992", "vehicle_speed": "0", "vehicle_lat": "42.340576171875", "vehicle_bearing": "63", "vehicle_timestamp": "1512530822", "vehicle_label": "1621", "vehicle_id": "y1621"}}, {"pre_away": "317", "trip_id": "35272376", "pre_dt": "1512531202", "sch_dep_dt": "1512531240", "sch_arr_dt": "1512531240", "trip_name": "10:12 pm from Forest Hills Station to Back Bay Station", "trip_headsign": "Back Bay", "vehicle": {"vehicle_lon": "-71.0919570922852", "vehicle_speed": "0", "vehicle_lat": "42.339038848877", "vehicle_bearing": "63", "vehicle_timestamp": "1512530817", "vehicle_label": "1642", "vehicle_id": "y1642"}}, {"pre_away": "1647", "trip_id": "35272360", "pre_dt": "1512532532", "sch_dep_dt": "1512532680", "sch_arr_dt": "1512532680", "trip_name": "10:36 pm from Forest Hills Station to Back Bay Station", "trip_headsign": "Back Bay"}, {"pre_away": "2367", "trip_id": "35272399", "pre_dt": "1512533252", "sch_dep_dt": "1512533280", "sch_arr_dt": "1512533280", "trip_name": "10:48 pm from Forest Hills Station to Back Bay Station", "trip_headsign": "Back Bay"}, {"pre_away": "3807", "trip_id": "35272378", "pre_dt": "1512534692", "sch_dep_dt": "1512534540", "sch_arr_dt": "1512534540", "trip_name": "11:12 pm from Forest Hills Station to Back Bay Station", "trip_headsign": "Back Bay"}], "time": 1512530890.020487}, "3824": {"info": [{"pre_away": "248", "trip_id": "35272387", "pre_dt": "1512531163", "sch_dep_dt": "1512530520", "sch_arr_dt": "1512530520", "trip_name": "10:00 pm from Forest Hills Station to Back Bay Station", "trip_headsign": "Back Bay", "vehicle": {"vehicle_lon": "-71.0833053588867", "vehicle_speed": "0", "vehicle_lat": "42.3439712524414", "vehicle_bearing": "40", "vehicle_timestamp": "1512530882", "vehicle_label": "1621", "vehicle_id": "y1621"}}, {"pre_away": "323", "trip_id": "35272376", "pre_dt": "1512531238", "sch_dep_dt": "1512531240", "sch_arr_dt": "1512531240", "trip_name": "10:12 pm from Forest Hills Station to Back Bay Station", "trip_headsign": "Back Bay", "vehicle": {"vehicle_lon": "-71.0883636474609", "vehicle_speed": "0", "vehicle_lat": "42.3405227661133", "vehicle_bearing": "63", "vehicle_timestamp": "1512530894", "vehicle_label": "1642", "vehicle_id": "y1642"}}, {"pre_away": "1617", "trip_id": "35272360", "pre_dt": "1512532532", "sch_dep_dt": "1512532680", "sch_arr_dt": "1512532680", "trip_name": "10:36 pm from Forest Hills Station to Back Bay Station", "trip_headsign": "Back Bay"}, {"pre_away": "2337", "trip_id": "35272399", "pre_dt": "1512533252", "sch_dep_dt": "1512533280", "sch_arr_dt": "1512533280", "trip_name": "10:48 pm from Forest Hills Station to Back Bay Station", "trip_headsign": "Back Bay"}, {"pre_away": "3777", "trip_id": "35272378", "pre_dt": "1512534692", "sch_dep_dt": "1512534540", "sch_arr_dt": "1512534540", "trip_name": "11:12 pm from Forest Hills Station to Back Bay Station", "trip_headsign": "Back Bay"}], "time": 1512530920.162148}, "3825": {"info": [{"pre_away": "211", "trip_id": "35272387", "pre_dt": "1512531156", "sch_dep_dt": "1512530520", "sch_arr_dt": "1512530520", "trip_name": "10:00 pm from Forest Hills Station to Back Bay Station", "trip_headsign": "Back Bay", "vehicle": {"vehicle_lon": "-71.0833053588867", "vehicle_speed": "0", "vehicle_lat": "42.3439712524414", "vehicle_bearing": "40", "vehicle_timestamp": "1512530882", "vehicle_label": "1621", "vehicle_id": "y1621"}}, {"pre_away": "291", "trip_id": "35272376", "pre_dt": "1512531236", "sch_dep_dt": "1512531240", "sch_arr_dt": "1512531240", "trip_name": "10:12 pm from Forest Hills Station to Back Bay Station", "trip_headsign": "Back Bay", "vehicle": {"vehicle_lon": "-71.0883636474609", "vehicle_speed": "0", "vehicle_lat": "42.3405227661133", "vehicle_bearing": "63", "vehicle_timestamp": "1512530894", "vehicle_label": "1642", "vehicle_id": "y1642"}}, {"pre_away": "1587", "trip_id": "35272360", "pre_dt": "1512532532", "sch_dep_dt": "1512532680", "sch_arr_dt": "1512532680", "trip_name": "10:36 pm from Forest Hills Station to Back Bay Station", "trip_headsign": "Back Bay"}, {"pre_away": "2307", "trip_id": "35272399", "pre_dt": "1512533252", "sch_dep_dt": "1512533280", "sch_arr_dt": "1512533280", "trip_name": "10:48 pm from Forest Hills Station to Back Bay Station", "trip_headsign": "Back Bay"}, {"pre_away": "3747", "trip_id": "35272378", "pre_dt": "1512534692", "sch_dep_dt": "1512534540", "sch_arr_dt": "1512534540", "trip_name": "11:12 pm from Forest Hills Station to Back Bay Station", "trip_headsign": "Back Bay"}], "time": 1512530950.314398}, "3826": {"info": [{"pre_away": "181", "trip_id": "35272387", "pre_dt": "1512531156", "sch_dep_dt": "1512530520", "sch_arr_dt": "1512530520", "trip_name": "10:00 pm from Forest Hills Station to Back Bay Station", "trip_headsign": "Back Bay", "vehicle": {"vehicle_lon": "-71.0833053588867", "vehicle_speed": "0", "vehicle_lat": "42.3439712524414", "vehicle_bearing": "40", "vehicle_timestamp": "1512530882", "vehicle_label": "1621", "vehicle_id": "y1621"}}, {"pre_away": "261", "trip_id": "35272376", "pre_dt": "1512531236", "sch_dep_dt": "1512531240", "sch_arr_dt": "1512531240", "trip_name": "10:12 pm from Forest Hills Station to Back Bay Station", "trip_headsign": "Back Bay", "vehicle": {"vehicle_lon": "-71.0883636474609", "vehicle_speed": "0", "vehicle_lat": "42.3405227661133", "vehicle_bearing": "63", "vehicle_timestamp": "1512530894", "vehicle_label": "1642", "vehicle_id": "y1642"}}, {"pre_away": "1557", "trip_id": "35272360", "pre_dt": "1512532532", "sch_dep_dt": "1512532680", "sch_arr_dt": "1512532680", "trip_name": "10:36 pm from Forest Hills Station to Back Bay Station", "trip_headsign": "Back Bay"}, {"pre_away": "2277", "trip_id": "35272399", "pre_dt": "1512533252", "sch_dep_dt": "1512533280", "sch_arr_dt": "1512533280", "trip_name": "10:48 pm from Forest Hills Station to Back Bay Station", "trip_headsign": "Back Bay"}, {"pre_away": "3717", "trip_id": "35272378", "pre_dt": "1512534692", "sch_dep_dt": "1512534540", "sch_arr_dt": "1512534540", "trip_name": "11:12 pm from Forest Hills Station to Back Bay Station", "trip_headsign": "Back Bay"}], "time": 1512530980.551744}, "3827": {"info": [{"pre_away": "139", "trip_id": "35272387", "pre_dt": "1512531144", "sch_dep_dt": "1512530520", "sch_arr_dt": "1512530520", "trip_name": "10:00 pm from Forest Hills Station to Back Bay Station", "trip_headsign": "Back Bay", "vehicle": {"vehicle_lon": "-71.0828857421875", "vehicle_speed": "0", "vehicle_lat": "42.3458557128906", "vehicle_bearing": "280", "vehicle_timestamp": "1512530942", "vehicle_label": "1621", "vehicle_id": "y1621"}}, {"pre_away": "242", "trip_id": "35272376", "pre_dt": "1512531247", "sch_dep_dt": "1512531240", "sch_arr_dt": "1512531240", "trip_name": "10:12 pm from Forest Hills Station to Back Bay Station", "trip_headsign": "Back Bay", "vehicle": {"vehicle_lon": "-71.0845718383789", "vehicle_speed": "0", "vehicle_lat": "42.3430137634277", "vehicle_bearing": "42", "vehicle_timestamp": "1512530954", "vehicle_label": "1642", "vehicle_id": "y1642"}}, {"pre_away": "1527", "trip_id": "35272360", "pre_dt": "1512532532", "sch_dep_dt": "1512532680", "sch_arr_dt": "1512532680", "trip_name": "10:36 pm from Forest Hills Station to Back Bay Station", "trip_headsign": "Back Bay"}, {"pre_away": "2247", "trip_id": "35272399", "pre_dt": "1512533252", "sch_dep_dt": "1512533280", "sch_arr_dt": "1512533280", "trip_name": "10:48 pm from Forest Hills Station to Back Bay Station", "trip_headsign": "Back Bay"}, {"pre_away": "3687", "trip_id": "35272378", "pre_dt": "1512534692", "sch_dep_dt": "1512534540", "sch_arr_dt": "1512534540", "trip_name": "11:12 pm from Forest Hills Station to Back Bay Station", "trip_headsign": "Back Bay"}], "time": 1512531010.875027}, "3828": {"info": [{"pre_away": "115", "trip_id": "35272387", "pre_dt": "1512531150", "sch_dep_dt": "1512530520", "sch_arr_dt": "1512530520", "trip_name": "10:00 pm from Forest Hills Station to Back Bay Station", "trip_headsign": "Back Bay", "vehicle": {"vehicle_lon": "-71.0828857421875", "vehicle_speed": "0", "vehicle_lat": "42.3458557128906", "vehicle_bearing": "280", "vehicle_timestamp": "1512530942", "vehicle_label": "1621", "vehicle_id": "y1621"}}, {"pre_away": "212", "trip_id": "35272376", "pre_dt": "1512531247", "sch_dep_dt": "1512531240", "sch_arr_dt": "1512531240", "trip_name": "10:12 pm from Forest Hills Station to Back Bay Station", "trip_headsign": "Back Bay", "vehicle": {"vehicle_lon": "-71.0845718383789", "vehicle_speed": "0", "vehicle_lat": "42.3430137634277", "vehicle_bearing": "42", "vehicle_timestamp": "1512530954", "vehicle_label": "1642", "vehicle_id": "y1642"}}, {"pre_away": "1497", "trip_id": "35272360", "pre_dt": "1512532532", "sch_dep_dt": "1512532680", "sch_arr_dt": "1512532680", "trip_name": "10:36 pm from Forest Hills Station to Back Bay Station", "trip_headsign": "Back Bay"}, {"pre_away": "2217", "trip_id": "35272399", "pre_dt": "1512533252", "sch_dep_dt": "1512533280", "sch_arr_dt": "1512533280", "trip_name": "10:48 pm from Forest Hills Station to Back Bay Station", "trip_headsign": "Back Bay"}, {"pre_away": "3657", "trip_id": "35272378", "pre_dt": "1512534692", "sch_dep_dt": "1512534540", "sch_arr_dt": "1512534540", "trip_name": "11:12 pm from Forest Hills Station to Back Bay Station", "trip_headsign": "Back Bay"}], "time": 1512531041.023186}, "3829": {"info": [{"pre_away": "82", "trip_id": "35272387", "pre_dt": "1512531148", "sch_dep_dt": "1512530520", "sch_arr_dt": "1512530520", "trip_name": "10:00 pm from Forest Hills Station to Back Bay Station", "trip_headsign": "Back Bay", "vehicle": {"vehicle_lon": "-71.0848693847656", "vehicle_speed": "0", "vehicle_lat": "42.3480987548828", "vehicle_bearing": "70", "vehicle_timestamp": "1512531022", "vehicle_label": "1621", "vehicle_id": "y1621"}}, {"pre_away": "181", "trip_id": "35272376", "pre_dt": "1512531247", "sch_dep_dt": "1512531240", "sch_arr_dt": "1512531240", "trip_name": "10:12 pm from Forest Hills Station to Back Bay Station", "trip_headsign": "Back Bay", "vehicle": {"vehicle_lon": "-71.0819244384766", "vehicle_speed": "0", "vehicle_lat": "42.3451995849609", "vehicle_bearing": "41", "vehicle_timestamp": "1512531014", "vehicle_label": "1642", "vehicle_id": "y1642"}}, {"pre_away": "1466", "trip_id": "35272360", "pre_dt": "1512532532", "sch_dep_dt": "1512532680", "sch_arr_dt": "1512532680", "trip_name": "10:36 pm from Forest Hills Station to Back Bay Station", "trip_headsign": "Back Bay"}, {"pre_away": "2186", "trip_id": "35272399", "pre_dt": "1512533252", "sch_dep_dt": "1512533280", "sch_arr_dt": "1512533280", "trip_name": "10:48 pm from Forest Hills Station to Back Bay Station", "trip_headsign": "Back Bay"}, {"pre_away": "3626", "trip_id": "35272378", "pre_dt": "1512534692", "sch_dep_dt": "1512534540", "sch_arr_dt": "1512534540", "trip_name": "11:12 pm from Forest Hills Station to Back Bay Station", "trip_headsign": "Back Bay"}], "time": 1512531071.160382}, "3830": {"info": [{"pre_away": "52", "trip_id": "35272387", "pre_dt": "1512531148", "sch_dep_dt": "1512530520", "sch_arr_dt": "1512530520", "trip_name": "10:00 pm from Forest Hills Station to Back Bay Station", "trip_headsign": "Back Bay", "vehicle": {"vehicle_lon": "-71.0848693847656", "vehicle_speed": "0", "vehicle_lat": "42.3480987548828", "vehicle_bearing": "70", "vehicle_timestamp": "1512531022", "vehicle_label": "1621", "vehicle_id": "y1621"}}, {"pre_away": "180", "trip_id": "35272376", "pre_dt": "1512531276", "sch_dep_dt": "1512531240", "sch_arr_dt": "1512531240", "trip_name": "10:12 pm from Forest Hills Station to Back Bay Station", "trip_headsign": "Back Bay", "vehicle": {"vehicle_lon": "-71.0819244384766", "vehicle_speed": "0", "vehicle_lat": "42.3451995849609", "vehicle_bearing": "41", "vehicle_timestamp": "1512531014", "vehicle_label": "1642", "vehicle_id": "y1642"}}, {"pre_away": "1436", "trip_id": "35272360", "pre_dt": "1512532532", "sch_dep_dt": "1512532680", "sch_arr_dt": "1512532680", "trip_name": "10:36 pm from Forest Hills Station to Back Bay Station", "trip_headsign": "Back Bay"}, {"pre_away": "2156", "trip_id": "35272399", "pre_dt": "1512533252", "sch_dep_dt": "1512533280", "sch_arr_dt": "1512533280", "trip_name": "10:48 pm from Forest Hills Station to Back Bay Station", "trip_headsign": "Back Bay"}, {"pre_away": "3596", "trip_id": "35272378", "pre_dt": "1512534692", "sch_dep_dt": "1512534540", "sch_arr_dt": "1512534540", "trip_name": "11:12 pm from Forest Hills Station to Back Bay Station", "trip_headsign": "Back Bay"}], "time": 1512531101.319681}, "3831": {"info": [{"pre_away": "6", "trip_id": "35272387", "pre_dt": "1512531132", "sch_dep_dt": "1512530520", "sch_arr_dt": "1512530520", "trip_name": "10:00 pm from Forest Hills Station to Back Bay Station", "trip_headsign": "Back Bay", "vehicle": {"vehicle_lon": "-71.0799026489258", "vehicle_speed": "0", "vehicle_lat": "42.3494110107422", "vehicle_bearing": "70", "vehicle_timestamp": "1512531083", "vehicle_label": "1621", "vehicle_id": "y1621"}}, {"pre_away": "150", "trip_id": "35272376", "pre_dt": "1512531276", "sch_dep_dt": "1512531240", "sch_arr_dt": "1512531240", "trip_name": "10:12 pm from Forest Hills Station to Back Bay Station", "trip_headsign": "Back Bay", "vehicle": {"vehicle_lon": "-71.0828628540039", "vehicle_speed": "0", "vehicle_lat": "42.3458404541016", "vehicle_bearing": "280", "vehicle_timestamp": "1512531074", "vehicle_label": "1642", "vehicle_id": "y1642"}}, {"pre_away": "1406", "trip_id": "35272360", "pre_dt": "1512532532", "sch_dep_dt": "1512532680", "sch_arr_dt": "1512532680", "trip_name": "10:36 pm from Forest Hills Station to Back Bay Station", "trip_headsign": "Back Bay"}, {"pre_away": "2126", "trip_id": "35272399", "pre_dt": "1512533252", "sch_dep_dt": "1512533280", "sch_arr_dt": "1512533280", "trip_name": "10:48 pm from Forest Hills Station to Back Bay Station", "trip_headsign": "Back Bay"}, {"pre_away": "3566", "trip_id": "35272378", "pre_dt": "1512534692", "sch_dep_dt": "1512534540", "sch_arr_dt": "1512534540", "trip_name": "11:12 pm from Forest Hills Station to Back Bay Station", "trip_headsign": "Back Bay"}], "time": 1512531131.495045}, "3832": {"info": [{"pre_away": "119", "trip_id": "35272376", "pre_dt": "1512531276", "sch_dep_dt": "1512531240", "sch_arr_dt": "1512531240", "trip_name": "10:12 pm from Forest Hills Station to Back Bay Station", "trip_headsign": "Back Bay", "vehicle": {"vehicle_lon": "-71.0828628540039", "vehicle_speed": "0", "vehicle_lat": "42.3458404541016", "vehicle_bearing": "280", "vehicle_timestamp": "1512531074", "vehicle_label": "1642", "vehicle_id": "y1642"}}, {"pre_away": "1375", "trip_id": "35272360", "pre_dt": "1512532532", "sch_dep_dt": "1512532680", "sch_arr_dt": "1512532680", "trip_name": "10:36 pm from Forest Hills Station to Back Bay Station", "trip_headsign": "Back Bay"}, {"pre_away": "2095", "trip_id": "35272399", "pre_dt": "1512533252", "sch_dep_dt": "1512533280", "sch_arr_dt": "1512533280", "trip_name": "10:48 pm from Forest Hills Station to Back Bay Station", "trip_headsign": "Back Bay"}, {"pre_away": "3535", "trip_id": "35272378", "pre_dt": "1512534692", "sch_dep_dt": "1512534540", "sch_arr_dt": "1512534540", "trip_name": "11:12 pm from Forest Hills Station to Back Bay Station", "trip_headsign": "Back Bay"}], "time": 1512531162.59673}, "3833": {"info": [{"pre_away": "89", "trip_id": "35272376", "pre_dt": "1512531276", "sch_dep_dt": "1512531240", "sch_arr_dt": "1512531240", "trip_name": "10:12 pm from Forest Hills Station to Back Bay Station", "trip_headsign": "Back Bay", "vehicle": {"vehicle_lon": "-71.0828628540039", "vehicle_speed": "0", "vehicle_lat": "42.3458404541016", "vehicle_bearing": "280", "vehicle_timestamp": "1512531074", "vehicle_label": "1642", "vehicle_id": "y1642"}}, {"pre_away": "1345", "trip_id": "35272360", "pre_dt": "1512532532", "sch_dep_dt": "1512532680", "sch_arr_dt": "1512532680", "trip_name": "10:36 pm from Forest Hills Station to Back Bay Station", "trip_headsign": "Back Bay"}, {"pre_away": "2065", "trip_id": "35272399", "pre_dt": "1512533252", "sch_dep_dt": "1512533280", "sch_arr_dt": "1512533280", "trip_name": "10:48 pm from Forest Hills Station to Back Bay Station", "trip_headsign": "Back Bay"}, {"pre_away": "3505", "trip_id": "35272378", "pre_dt": "1512534692", "sch_dep_dt": "1512534540", "sch_arr_dt": "1512534540", "trip_name": "11:12 pm from Forest Hills Station to Back Bay Station", "trip_headsign": "Back Bay"}], "time": 1512531192.893031}, "3834": {"info": [{"pre_away": "59", "trip_id": "35272376", "pre_dt": "1512531276", "sch_dep_dt": "1512531240", "sch_arr_dt": "1512531240", "trip_name": "10:12 pm from Forest Hills Station to Back Bay Station", "trip_headsign": "Back Bay", "vehicle": {"vehicle_lon": "-71.0828628540039", "vehicle_speed": "0", "vehicle_lat": "42.3458404541016", "vehicle_bearing": "280", "vehicle_timestamp": "1512531074", "vehicle_label": "1642", "vehicle_id": "y1642"}}, {"pre_away": "1315", "trip_id": "35272360", "pre_dt": "1512532532", "sch_dep_dt": "1512532680", "sch_arr_dt": "1512532680", "trip_name": "10:36 pm from Forest Hills Station to Back Bay Station", "trip_headsign": "Back Bay"}, {"pre_away": "2035", "trip_id": "35272399", "pre_dt": "1512533252", "sch_dep_dt": "1512533280", "sch_arr_dt": "1512533280", "trip_name": "10:48 pm from Forest Hills Station to Back Bay Station", "trip_headsign": "Back Bay"}, {"pre_away": "3475", "trip_id": "35272378", "pre_dt": "1512534692", "sch_dep_dt": "1512534540", "sch_arr_dt": "1512534540", "trip_name": "11:12 pm from Forest Hills Station to Back Bay Station", "trip_headsign": "Back Bay"}], "time": 1512531223.043474}, "3835": {"info": [{"pre_away": "72", "trip_id": "35272376", "pre_dt": "1512531319", "sch_dep_dt": "1512531240", "sch_arr_dt": "1512531240", "trip_name": "10:12 pm from Forest Hills Station to Back Bay Station", "trip_headsign": "Back Bay", "vehicle": {"vehicle_lon": "-71.084831237793", "vehicle_speed": "0", "vehicle_lat": "42.3480987548828", "vehicle_bearing": "70", "vehicle_timestamp": "1512531193", "vehicle_label": "1642", "vehicle_id": "y1642"}}, {"pre_away": "1285", "trip_id": "35272360", "pre_dt": "1512532532", "sch_dep_dt": "1512532680", "sch_arr_dt": "1512532680", "trip_name": "10:36 pm from Forest Hills Station to Back Bay Station", "trip_headsign": "Back Bay", "vehicle": {"vehicle_lon": "-71.1150588989258", "vehicle_speed": "0", "vehicle_lat": "42.2995872497559", "vehicle_bearing": "216", "vehicle_timestamp": "1512531202", "vehicle_label": "1640", "vehicle_id": "y1640"}}, {"pre_away": "2005", "trip_id": "35272399", "pre_dt": "1512533252", "sch_dep_dt": "1512533280", "sch_arr_dt": "1512533280", "trip_name": "10:48 pm from Forest Hills Station to Back Bay Station", "trip_headsign": "Back Bay"}, {"pre_away": "3445", "trip_id": "35272378", "pre_dt": "1512534692", "sch_dep_dt": "1512534540", "sch_arr_dt": "1512534540", "trip_name": "11:12 pm from Forest Hills Station to Back Bay Station", "trip_headsign": "Back Bay"}], "time": 1512531253.199133}, "3836": {"info": [{"pre_away": "42", "trip_id": "35272376", "pre_dt": "1512531319", "sch_dep_dt": "1512531240", "sch_arr_dt": "1512531240", "trip_name": "10:12 pm from Forest Hills Station to Back Bay Station", "trip_headsign": "Back Bay", "vehicle": {"vehicle_lon": "-71.084831237793", "vehicle_speed": "0", "vehicle_lat": "42.3480987548828", "vehicle_bearing": "70", "vehicle_timestamp": "1512531193", "vehicle_label": "1642", "vehicle_id": "y1642"}}, {"pre_away": "1255", "trip_id": "35272360", "pre_dt": "1512532532", "sch_dep_dt": "1512532680", "sch_arr_dt": "1512532680", "trip_name": "10:36 pm from Forest Hills Station to Back Bay Station", "trip_headsign": "Back Bay", "vehicle": {"vehicle_lon": "-71.1150588989258", "vehicle_speed": "0", "vehicle_lat": "42.2995872497559", "vehicle_bearing": "216", "vehicle_timestamp": "1512531202", "vehicle_label": "1640", "vehicle_id": "y1640"}}, {"pre_away": "1975", "trip_id": "35272399", "pre_dt": "1512533252", "sch_dep_dt": "1512533280", "sch_arr_dt": "1512533280", "trip_name": "10:48 pm from Forest Hills Station to Back Bay Station", "trip_headsign": "Back Bay"}, {"pre_away": "3415", "trip_id": "35272378", "pre_dt": "1512534692", "sch_dep_dt": "1512534540", "sch_arr_dt": "1512534540", "trip_name": "11:12 pm from Forest Hills Station to Back Bay Station", "trip_headsign": "Back Bay"}], "time": 1512531283.352752}, "3837": {"info": [{"pre_away": "1225", "trip_id": "35272360", "pre_dt": "1512532532", "sch_dep_dt": "1512532680", "sch_arr_dt": "1512532680", "trip_name": "10:36 pm from Forest Hills Station to Back Bay Station", "trip_headsign": "Back Bay", "vehicle": {"vehicle_lon": "-71.1143493652344", "vehicle_speed": "0", "vehicle_lat": "42.2998123168945", "vehicle_bearing": "216", "vehicle_timestamp": "1512531262", "vehicle_label": "1640", "vehicle_id": "y1640"}}, {"pre_away": "1947", "trip_id": "35272399", "pre_dt": "1512533254", "sch_dep_dt": "1512533280", "sch_arr_dt": "1512533280", "trip_name": "10:48 pm from Forest Hills Station to Back Bay Station", "trip_headsign": "Back Bay"}, {"pre_away": "3385", "trip_id": "35272378", "pre_dt": "1512534692", "sch_dep_dt": "1512534540", "sch_arr_dt": "1512534540", "trip_name": "11:12 pm from Forest Hills Station to Back Bay Station", "trip_headsign": "Back Bay"}], "time": 1512531313.501137}, "3838": {"info": [{"pre_away": "1195", "trip_id": "35272360", "pre_dt": "1512532532", "sch_dep_dt": "1512532680", "sch_arr_dt": "1512532680", "trip_name": "10:36 pm from Forest Hills Station to Back Bay Station", "trip_headsign": "Back Bay", "vehicle": {"vehicle_lon": "-71.1143493652344", "vehicle_speed": "0", "vehicle_lat": "42.2998123168945", "vehicle_bearing": "216", "vehicle_timestamp": "1512531262", "vehicle_label": "1640", "vehicle_id": "y1640"}}, {"pre_away": "1917", "trip_id": "35272399", "pre_dt": "1512533254", "sch_dep_dt": "1512533280", "sch_arr_dt": "1512533280", "trip_name": "10:48 pm from Forest Hills Station to Back Bay Station", "trip_headsign": "Back Bay"}, {"pre_away": "3355", "trip_id": "35272378", "pre_dt": "1512534692", "sch_dep_dt": "1512534540", "sch_arr_dt": "1512534540", "trip_name": "11:12 pm from Forest Hills Station to Back Bay Station", "trip_headsign": "Back Bay"}], "time": 1512531343.847448}, "3839": {"info": [{"pre_away": "1165", "trip_id": "35272360", "pre_dt": "1512532532", "sch_dep_dt": "1512532680", "sch_arr_dt": "1512532680", "trip_name": "10:36 pm from Forest Hills Station to Back Bay Station", "trip_headsign": "Back Bay", "vehicle": {"vehicle_lon": "-71.1143493652344", "vehicle_speed": "0", "vehicle_lat": "42.2998123168945", "vehicle_bearing": "216", "vehicle_timestamp": "1512531322", "vehicle_label": "1640", "vehicle_id": "y1640"}}, {"pre_away": "1887", "trip_id": "35272399", "pre_dt": "1512533254", "sch_dep_dt": "1512533280", "sch_arr_dt": "1512533280", "trip_name": "10:48 pm from Forest Hills Station to Back Bay Station", "trip_headsign": "Back Bay"}, {"pre_away": "3325", "trip_id": "35272378", "pre_dt": "1512534692", "sch_dep_dt": "1512534540", "sch_arr_dt": "1512534540", "trip_name": "11:12 pm from Forest Hills Station to Back Bay Station", "trip_headsign": "Back Bay"}, {"pre_away": "4765", "trip_id": "35272363", "pre_dt": "1512536132", "sch_dep_dt": "1512535980", "sch_arr_dt": "1512535980", "trip_name": "11:36 pm from Forest Hills Station to Back Bay Station", "trip_headsign": "Back Bay"}], "time": 1512531374.08083}}